{
  "last_updated": "2026-03-14T01:55:00Z",
  "token_health": {
    "price": 0.001376,
    "price_change_m5": 0.0,
    "price_change_1h": 0.42,
    "price_change_6h": -0.59,
    "price_change_24h": -7.6,
    "market_cap": 1375623,
    "liquidity": 214606.89,
    "volume_m5": 0,
    "volume_1h": 355.99,
    "volume_6h": 6186.61,
    "volume_24h": 79726.97,
    "volume_ratio_1h": 0.11,
    "buys_24h": 334,
    "sells_24h": 325,
    "buys_1h": 3,
    "sells_1h": 5,
    "holders": 16798,
    "holder_trend": 0,
    "sentiment": "neutral",
    "_source": "dexscreener",
    "cmc_rank": 1783,
    "total_volume_24h": 927594.12541723,
    "volume_change_pct": -1.9,
    "volume_change_usd": -17985.69,
    "mcap_change_pct": 1.11,
    "mcap_change_usd": 15155,
    "liquidity_change_pct": 1.15,
    "liquidity_change_usd": 2432.59,
    "biggest_trades": {
      "biggest_buy_usd": 2557.55,
      "biggest_buy_tx": "5Sp9Qdn92PgCuaTcQiRCA9CRzWufUdUdMoRC9dcfrSt5evJbVDdZ4sNH9ABv3569Z4mf7cfGthMzP1EqpGhwqzgG",
      "biggest_buy_wallet": "",
      "biggest_buy_time": "2026-03-02T00:56:15Z",
      "biggest_sell_usd": 1366.79,
      "biggest_sell_tx": "2ouyoBbrW25kZun4LoUPt4WkaVxktpd273iPFJBK7RqPwvE93BqBQcXGQpyK8GhchpJyxZNmwb1fkdiXQCg4YpWx",
      "biggest_sell_wallet": "",
      "biggest_sell_time": "2026-03-02T03:57:46Z",
      "_trades_in_window": 300
    }
  },
  "social_pulse": {
    "twitter_followers": 1702,
    "follower_change_24h": 4,
    "posting_streak_days": 0,
    "engagement_rate": 4.862,
    "_source": "nitter_rss+twitter_cdn",
    "best_tweet_week": {
      "tweet_id": "2030317259894218981",
      "tweet_url": "https://x.com/67coinX/status/2030317259894218981",
      "screen_name": "67coinX",
      "name": "67coinX",
      "avatar": "",
      "text": "Two numbers to unite the world. 67 billion human beings.\n\n@duolingo \n\n#67to67billion https://t.co/NxWQIuCAZG",
      "likes": 79,
      "replies": 24,
      "retweets": 18,
      "date": "2026-03-07"
    },
    "best_tweet_2d": {
      "tweet_id": "2031118201212354707",
      "tweet_url": "https://x.com/67coinX/status/2031118201212354707",
      "screen_name": "67coinX",
      "name": "67coinX",
      "avatar": "",
      "text": "Some 67 moments leave you speechless...\n\n#67to67billion https://t.co/cN55YAIDZu",
      "likes": 69,
      "replies": 17,
      "retweets": 19,
      "date": "2026-03-09"
    },
    "avg_engagement": 83.2,
    "twitter_followers_updated_at": "2026-03-01T21:30:22.077518Z",
    "total_engagement_7d": 1082,
    "follower_history": [
      {
        "date": "2026-02-24",
        "count": 1628
      },
      {
        "date": "2026-02-25",
        "count": 1628
      },
      {
        "date": "2026-02-26",
        "count": 1628
      },
      {
        "date": "2026-02-27",
        "count": 1628
      },
      {
        "date": "2026-02-28",
        "count": 1659
      },
      {
        "date": "2026-03-01",
        "count": 1659
      },
      {
        "date": "2026-03-02",
        "count": 1659
      },
      {
        "date": "2026-03-06",
        "count": 1670
      },
      {
        "date": "2026-03-07",
        "count": 1670
      },
      {
        "date": "2026-03-08",
        "count": 1683
      },
      {
        "date": "2026-03-10",
        "count": 1689
      },
      {
        "date": "2026-03-11",
        "count": 1698
      },
      {
        "date": "2026-03-13",
        "count": 1702
      }
    ],
    "follower_growth_7d": 31,
    "content_type_stats": {
      "thesis": {
        "count": 2,
        "total_eng": 178,
        "avg_eng": 89.0
      },
      "other": {
        "count": 7,
        "total_eng": 553,
        "avg_eng": 79.0
      },
      "meme": {
        "count": 2,
        "total_eng": 154,
        "avg_eng": 77.0
      },
      "community": {
        "count": 1,
        "total_eng": 122,
        "avg_eng": 122.0
      },
      "announcement": {
        "count": 1,
        "total_eng": 75,
        "avg_eng": 75.0
      }
    },
    "best_content_type": "meme",
    "x_community_members": 10028,
    "x_community_delta_24h": 23,
    "x_community_id": "1987949705322508569",
    "mentions": [],
    "x_community_last_scrape": 1772996555.780906,
    "follower_change_3d": 13,
    "follower_change_7d": 43,
    "community_tweets": [
      {
        "tweet_id": "2031013906425266617",
        "tweet_url": "https://x.com//status/2031013906425266617",
        "screen_name": "",
        "name": "",
        "avatar": "",
        "text": "punch was a bigger fumble then 67coin\n\n300 mil runner",
        "likes": 342,
        "replies": 38,
        "retweets": 16,
        "date": "2026-03-09"
      },
      {
        "tweet_id": "2031082112082915487",
        "tweet_url": "https://x.com//status/2031082112082915487",
        "screen_name": "",
        "name": "",
        "avatar": "",
        "text": "@prxnterr I think the Frasier one wins. I don't think any of these new chud coins can beat it. \n\n I get the criticism of it being not just simply -chud as a negative. But the 67 coin that won was 'the official 67 coin' instead of '67coin'. \n\nThe name matters, but the ticker matte",
        "likes": 13,
        "replies": 1,
        "retweets": 2,
        "date": "2026-03-09"
      }
    ],
    "total_views_recent": 30682,
    "total_likes_recent": 886,
    "follower_change_3d_snap": 32
  },
  "community": {
    "discord_members": 0,
    "active_7d": 1870,
    "new_joins_24h": 10,
    "open_tickets": 3,
    "unanswered_posts": 7,
    "telegram_members": 0,
    "watchlist_count": 8262,
    "top_exchanges": [
      {
        "exchange": "XT.COM",
        "pair": "67/USDT",
        "volume_usd": 493822,
        "is_dex": false,
        "logo": "https://coin-images.coingecko.com/markets/images/404/small/xt_logo_%E7%BB%BF.png?1761205934"
      },
      {
        "exchange": "KCEX",
        "pair": "67/USDT",
        "volume_usd": 151897,
        "is_dex": false,
        "logo": "https://coin-images.coingecko.com/markets/images/11953/small/photo_2025-05-27_02-31-22.jpg?1748284326"
      },
      {
        "exchange": "PumpSwap (DEX)",
        "pair": "DEX pool",
        "volume_usd": 116454,
        "is_dex": true,
        "logo": "https://coin-images.coingecko.com/markets/images/11879/small/pumpfun.jpg?1740376296"
      },
      {
        "exchange": "LBank",
        "pair": "67/USDT",
        "volume_usd": 100838,
        "is_dex": false,
        "logo": "https://coin-images.coingecko.com/markets/images/118/small/LBank_200_200.png?1757347528"
      },
      {
        "exchange": "MEXC",
        "pair": "67/USDT",
        "volume_usd": 64619,
        "is_dex": false,
        "logo": "https://coin-images.coingecko.com/markets/images/409/small/logo_new.png?1743600043"
      },
      {
        "exchange": "Bilaxy",
        "pair": "67/USDT",
        "volume_usd": 17877.0,
        "is_dex": false,
        "logo": "https://coin-images.coingecko.com/markets/images/193/small/bilaxy.png?1706864324"
      }
    ],
    "sentiment_up_pct": 50.0,
    "sentiment_down_pct": 50.0,
    "online_now": 0,
    "discord_delta_24h": 0,
    "telegram_delta_24h": 0,
    "watchlist_delta_24h": 0,
    "recent_discord_activity": [
      {
        "type": "join",
        "user": "casiopriv870",
        "user_id": "1226223232445583402",
        "avatar": "https://cdn.discordapp.com/avatars/1226223232445583402/52f5803c7c4bd976686b7920c42073c6.webp?size=64",
        "time_ago": "12h ago",
        "detail": "Introduced in Discord"
      },
      {
        "type": "join",
        "user": "marziechockymilk",
        "user_id": "1464960465703665917",
        "avatar": "https://cdn.discordapp.com/avatars/1464960465703665917/8854b0674e382b8ded4eb2369db33973.webp?size=64",
        "time_ago": "12h ago",
        "detail": "Introduced in Discord"
      },
      {
        "type": "join",
        "user": "w3b8",
        "user_id": "908761821798871100",
        "avatar": "https://cdn.discordapp.com/avatars/908761821798871100/17ad82ac229b13afee48706e7fac2c34.webp?size=64",
        "time_ago": "15h ago",
        "detail": "Introduced in Discord"
      },
      {
        "type": "join",
        "user": "dyllpyckle",
        "user_id": "943205628367761408",
        "avatar": "https://cdn.discordapp.com/avatars/943205628367761408/5161093a6e9af36e5e3849a13ab291bd.webp?size=64",
        "time_ago": "1d ago",
        "detail": "Introduced in Discord"
      },
      {
        "type": "join",
        "user": "dimi_serb21",
        "user_id": "786965721614647326",
        "avatar": "https://cdn.discordapp.com/avatars/786965721614647326/3f8bb8124b5974e7f4427d7603f20226.webp?size=64",
        "time_ago": "1d ago",
        "detail": "Introduced in Discord"
      },
      {
        "type": "join",
        "user": "jesuslovesyou05258",
        "user_id": "1344145084328972348",
        "avatar": "https://cdn.discordapp.com/avatars/1344145084328972348/8569adcbd36c70a7578c017bf5604ea5.webp?size=64",
        "time_ago": "4d ago",
        "detail": "Introduced in Discord"
      },
      {
        "type": "join",
        "user": "p4rty_p0ison",
        "user_id": "954906892168233040",
        "avatar": "https://cdn.discordapp.com/avatars/954906892168233040/1893824d878a661922d1b21ca7961b32.webp?size=64",
        "time_ago": "4d ago",
        "detail": "Introduced in Discord"
      },
      {
        "type": "join",
        "user": "ggauvin",
        "user_id": "965681608604647514",
        "avatar": "https://cdn.discordapp.com/avatars/965681608604647514/6c28a0cb30c603a25b288844e5c53e2e.webp?size=64",
        "time_ago": "5d ago",
        "detail": "Introduced in Discord"
      },
      {
        "type": "join",
        "user": "abguy0254",
        "user_id": "1387846802266656858",
        "avatar": "https://cdn.discordapp.com/avatars/1387846802266656858/c1c8b7358ca9fd42b54a446f5d1e9498.webp?size=64",
        "time_ago": "5d ago",
        "detail": "Introduced in Discord"
      },
      {
        "type": "join",
        "user": "pingbit",
        "user_id": "505736478341726221",
        "avatar": "https://cdn.discordapp.com/avatars/505736478341726221/c3f1121e6490f2524d1b5eb7cfb80799.webp?size=64",
        "time_ago": "7d ago",
        "detail": "Introduced in Discord"
      },
      {
        "type": "join",
        "user": "_335laranja_",
        "user_id": "829000178631442442",
        "avatar": "https://cdn.discordapp.com/avatars/829000178631442442/1f0e0ab306ed466ff75f0ca3fa14a64d.webp?size=64",
        "time_ago": "12d ago",
        "detail": "Introduced in Discord"
      },
      {
        "type": "join",
        "user": "hypex90",
        "user_id": "800399454636212224",
        "avatar": "https://cdn.discordapp.com/avatars/800399454636212224/7870225de3304313c6e17ed6abf2b4e8.webp?size=64",
        "time_ago": "17d ago",
        "detail": "Introduced in Discord"
      }
    ],
    "telegram_mod_events": [],
    "active_users_today": 16,
    "top_channels": [
      {
        "channel_id": "1458846146415034460",
        "name": "\ud83d\udcac-chat",
        "msgs_1h": 10
      },
      {
        "channel_id": "1458846213087432868",
        "name": "\ud83e\udd23-memes",
        "msgs_1h": 1
      }
    ],
    "top_channels_updated_at": 1772411491.747939,
    "x_community_members": 9900,
    "x_community_delta_24h": 100
  },
  "content_pipeline": {
    "scheduled_posts": [
      {
        "title": "Weekly Alpha Thread",
        "type": "thesis",
        "scheduled": "2026-02-24T18:00:00Z"
      },
      {
        "title": "67 Meme Drop #42",
        "type": "meme",
        "scheduled": "2026-02-25T12:00:00Z"
      },
      {
        "title": "Dev Update: Agent v2",
        "type": "culture_drop",
        "scheduled": "2026-02-25T20:00:00Z"
      },
      {
        "title": "Community Spotlight",
        "type": "culture_drop",
        "scheduled": "2026-02-26T15:00:00Z"
      }
    ],
    "last_post_timestamp": "2026-02-24T11:16:35.996258Z",
    "content_breakdown": {
      "meme": 34,
      "thesis": 22,
      "culture_drop": 28,
      "announcement": 16
    }
  },
  "agents": [
    {
      "name": "X Raid Bot",
      "status": "green",
      "last_run": "2026-03-03T00:25:52.119365Z",
      "errors_24h": 0,
      "schedule": "Auto (<10min tweets)"
    },
    {
      "name": "Data Updater",
      "status": "green",
      "last_run": "2026-03-03T00:25:52.119365Z",
      "errors_24h": 0,
      "schedule": "Every 30 min"
    },
    {
      "name": "Presence Bot",
      "status": "green",
      "last_run": "2026-03-03T00:25:52.119365Z",
      "errors_24h": 0,
      "schedule": "Every 5 min"
    },
    {
      "name": "Wallet Tracker",
      "status": "green",
      "last_run": "2026-03-03T00:25:52.119365Z",
      "errors_24h": 0,
      "schedule": "On demand"
    },
    {
      "name": "TikTok Scraper",
      "status": "red",
      "last_run": "2026-02-28T23:27:42.342193Z",
      "errors_24h": 0,
      "schedule": "Every 30 min"
    }
  ],
  "milestones": [
    {
      "label": "10K Holders",
      "current": 16798,
      "target": 10000
    },
    {
      "label": "5K Twitter Followers",
      "current": 1659,
      "target": 5000
    },
    {
      "label": "5K Discord Members",
      "current": 1449,
      "target": 5000
    },
    {
      "label": "$6.7M Market Cap",
      "current": 1375623,
      "target": 6700000
    }
  ],
  "recent_wins": [
    {
      "label": "Listed on 14 exchanges",
      "date": "2026-02-15"
    },
    {
      "label": "Listed on CoinMarketCap",
      "date": "2026-02-12"
    },
    {
      "label": "Listed on CoinGecko",
      "date": "2026-02-10"
    },
    {
      "label": "Mission Control v2 launched",
      "date": "2026-02-25"
    }
  ],
  "next_target": "10K Holders by March 15",
  "alerts": [
    {
      "type": "success",
      "message": "\ud83d\udd25 Near ALL-TIME HIGH! Only 0.0% away \u2014 $0.001376",
      "timestamp": "2026-03-02T11:32:20.014484Z"
    }
  ],
  "coingecko": {
    "coingecko_rank": 2669,
    "ath": 0.04363399,
    "ath_date": "2025-11-19",
    "ath_change_pct": -96.96,
    "atl": 7.72e-05,
    "price_change_7d": -54.89,
    "price_change_1h": 2.51,
    "watchlist_count": 8262,
    "telegram_members": 2257,
    "sentiment_up_pct": 50.0,
    "sentiment_down_pct": 50.0,
    "top_exchanges": [
      {
        "exchange": "XT.COM",
        "pair": "67/USDT",
        "volume_usd": 493822,
        "is_dex": false,
        "logo": "https://coin-images.coingecko.com/markets/images/404/small/xt_logo_%E7%BB%BF.png?1761205934"
      },
      {
        "exchange": "KCEX",
        "pair": "67/USDT",
        "volume_usd": 151897,
        "is_dex": false,
        "logo": "https://coin-images.coingecko.com/markets/images/11953/small/photo_2025-05-27_02-31-22.jpg?1748284326"
      },
      {
        "exchange": "PumpSwap (DEX)",
        "pair": "DEX pool",
        "volume_usd": 116454,
        "is_dex": true,
        "logo": "https://coin-images.coingecko.com/markets/images/11879/small/pumpfun.jpg?1740376296"
      },
      {
        "exchange": "LBank",
        "pair": "67/USDT",
        "volume_usd": 100838,
        "is_dex": false,
        "logo": "https://coin-images.coingecko.com/markets/images/118/small/LBank_200_200.png?1757347528"
      },
      {
        "exchange": "MEXC",
        "pair": "67/USDT",
        "volume_usd": 64619,
        "is_dex": false,
        "logo": "https://coin-images.coingecko.com/markets/images/409/small/logo_new.png?1743600043"
      },
      {
        "exchange": "Bilaxy",
        "pair": "67/USDT",
        "volume_usd": 17877.0,
        "is_dex": false,
        "logo": "https://coin-images.coingecko.com/markets/images/193/small/bilaxy.png?1706864324"
      }
    ],
    "_source": "coingecko"
  },
  "coinmarketcap": {
    "cmc_rank": 1783,
    "cmc_id": "38918",
    "price": 0.0013748696627709088,
    "volume_24h": 927594.12541723,
    "market_cap": 1374429.7044788222,
    "change_1h": 0.72620563,
    "change_24h": -8.60092439,
    "change_7d": -36.07748096,
    "change_30d": -65.45811279,
    "market_pairs": 45,
    "_source": "coinmarketcap"
  },
  "_snapshot_24h": {
    "timestamp": "2026-03-13T18:30:01.470603+00:00",
    "twitter_followers": 1698,
    "x_community_members": 10028,
    "discord_members": 1449,
    "telegram_members": 2432,
    "holders": 16585
  },
  "team_presence": {
    "767811814557089802": "idle",
    "965681608604647514": "dnd",
    "1444130836415905993": "offline",
    "1440075589557158100": "offline",
    "682831521396031498": "offline",
    "788495124061487154": "offline",
    "201710326347988993": "offline"
  },
  "presence_updated": "2026-03-02T11:25:07.588806Z",
  "tiktok_spotlight": [
    {
      "id": "7604202651743571214",
      "video_url": "https://www.tiktok.com/@67coin/video/7604202651743571214",
      "thumbnail_url": "/tiktok-thumbs/7604202651743571214.jpg",
      "plays": 10600,
      "likes": 0,
      "comments": 0,
      "description": ""
    },
    {
      "id": "7612781908325354765",
      "video_url": "https://www.tiktok.com/@67coin/video/7612781908325354765",
      "thumbnail_url": "/tiktok-thumbs/7612781908325354765.jpg",
      "plays": 24,
      "likes": 0,
      "comments": 0,
      "description": ""
    },
    {
      "id": "7612457142259420429",
      "video_url": "https://www.tiktok.com/@67coin/video/7612457142259420429",
      "thumbnail_url": "/tiktok-thumbs/7612457142259420429.jpg",
      "plays": 25,
      "likes": 0,
      "comments": 0,
      "description": ""
    },
    {
      "id": "7612078619019513102",
      "video_url": "https://www.tiktok.com/@67coin/video/7612078619019513102",
      "thumbnail_url": "/tiktok-thumbs/7612078619019513102.jpg",
      "plays": 22,
      "likes": 0,
      "comments": 0,
      "description": ""
    },
    {
      "id": "7611723330290257166",
      "video_url": "https://www.tiktok.com/@67coin/video/7611723330290257166",
      "thumbnail_url": "/tiktok-thumbs/7611723330290257166.jpg",
      "plays": 28,
      "likes": 0,
      "comments": 0,
      "description": ""
    },
    {
      "id": "7611332134107647246",
      "video_url": "https://www.tiktok.com/@67coin/video/7611332134107647246",
      "thumbnail_url": "/tiktok-thumbs/7611332134107647246.jpg",
      "plays": 2098,
      "likes": 0,
      "comments": 0,
      "description": ""
    },
    {
      "id": "7610562713697209614",
      "video_url": "https://www.tiktok.com/@67coin/video/7610562713697209614",
      "thumbnail_url": "/tiktok-thumbs/7610562713697209614.jpg",
      "plays": 2106,
      "likes": 0,
      "comments": 0,
      "description": ""
    },
    {
      "id": "7610184265048886541",
      "video_url": "https://www.tiktok.com/@67coin/video/7610184265048886541",
      "thumbnail_url": "/tiktok-thumbs/7610184265048886541.jpg",
      "plays": 2094,
      "likes": 0,
      "comments": 0,
      "description": ""
    },
    {
      "id": "7609859500383751438",
      "video_url": "https://www.tiktok.com/@67coin/video/7609859500383751438",
      "thumbnail_url": "/tiktok-thumbs/7609859500383751438.jpg",
      "plays": 5236,
      "likes": 0,
      "comments": 0,
      "description": ""
    },
    {
      "id": "7609480473043012878",
      "video_url": "https://www.tiktok.com/@67coin/video/7609480473043012878",
      "thumbnail_url": "/tiktok-thumbs/7609480473043012878.jpg",
      "plays": 3138,
      "likes": 0,
      "comments": 0,
      "description": ""
    },
    {
      "id": "7609101852583496974",
      "video_url": "https://www.tiktok.com/@67coin/video/7609101852583496974",
      "thumbnail_url": "/tiktok-thumbs/7609101852583496974.jpg",
      "plays": 5296,
      "likes": 0,
      "comments": 0,
      "description": ""
    },
    {
      "id": "7608622833979247886",
      "video_url": "https://www.tiktok.com/@67coin/video/7608622833979247886",
      "thumbnail_url": "/tiktok-thumbs/7608622833979247886.jpg",
      "plays": 3937,
      "likes": 0,
      "comments": 0,
      "description": ""
    }
  ],
  "instagram_spotlight": [],
  "raid_feed": [
    {
      "message_id": 6257,
      "text": "67",
      "tweet_url": "",
      "photo": "",
      "date": "2026-03-02T10:55:44Z",
      "chat_id": -1003708062172
    },
    {
      "message_id": 6249,
      "text": "Raid\n\nhttps://x.com/harrodfrances/status/2028418177248514449?s=46",
      "tweet_url": "https://x.com/i/web/status/2028418177248514449",
      "photo": "",
      "date": "2026-03-02T10:32:47Z",
      "chat_id": -1003708062172
    },
    {
      "message_id": 6248,
      "text": "Raid\n\nhttps://x.com/dedenovitaj/status/2028417814999007307?s=46",
      "tweet_url": "https://x.com/i/web/status/2028417814999007307",
      "photo": "",
      "date": "2026-03-02T10:31:17Z",
      "chat_id": -1003708062172
    },
    {
      "message_id": 6245,
      "text": "Raid\n\nhttps://x.com/harrodfrances/status/2028413888593547400?s=46",
      "tweet_url": "https://x.com/i/web/status/2028413888593547400",
      "photo": "",
      "date": "2026-03-02T10:15:42Z",
      "chat_id": -1003708062172
    },
    {
      "message_id": 6243,
      "text": "Raid \n\nhttps://x.com/i/status/2028411131945984308",
      "tweet_url": "https://x.com/i/web/status/2028411131945984308",
      "photo": "",
      "date": "2026-03-02T10:05:04Z",
      "chat_id": -1003708062172
    },
    {
      "message_id": 6240,
      "text": "",
      "tweet_url": "",
      "photo": "https://api.telegram.org/file/bot***REDACTED***/photos/file_4.jpg",
      "date": "2026-03-02T09:55:33Z",
      "chat_id": -1003708062172
    },
    {
      "message_id": 6237,
      "text": "Raid\n\nhttps://x.com/beraatkaratepe/status/2028406609689415781?s=46",
      "tweet_url": "https://x.com/i/web/status/2028406609689415781",
      "photo": "",
      "date": "2026-03-02T09:46:48Z",
      "chat_id": -1003708062172
    },
    {
      "message_id": 6212,
      "text": "Raid\n\nhttps://x.com/beraatkaratepe/status/2028376828902019450?s=46",
      "tweet_url": "https://x.com/i/web/status/2028376828902019450",
      "photo": "",
      "date": "2026-03-02T07:48:27Z",
      "chat_id": -1003708062172
    },
    {
      "message_id": 6211,
      "text": "Raid\n\nhttps://x.com/dedenovitaj/status/2028370901545214405?s=46",
      "tweet_url": "https://x.com/i/web/status/2028370901545214405",
      "photo": "",
      "date": "2026-03-02T07:24:52Z",
      "chat_id": -1003708062172
    },
    {
      "message_id": 6210,
      "text": "Raid\n\nhttps://x.com/beraatkaratepe/status/2028370675505795298?s=46",
      "tweet_url": "https://x.com/i/web/status/2028370675505795298",
      "photo": "",
      "date": "2026-03-02T07:23:57Z",
      "chat_id": -1003708062172
    },
    {
      "message_id": 6209,
      "text": "Raid\n\nhttps://x.com/dedenovitaj/status/2028370426661867982?s=46",
      "tweet_url": "https://x.com/i/web/status/2028370426661867982",
      "photo": "",
      "date": "2026-03-02T07:22:59Z",
      "chat_id": -1003708062172
    },
    {
      "message_id": 6208,
      "text": "Raid\n\nhttps://x.com/harrodfrances/status/2028369871478681710?s=46",
      "tweet_url": "https://x.com/i/web/status/2028369871478681710",
      "photo": "",
      "date": "2026-03-02T07:20:49Z",
      "chat_id": -1003708062172
    },
    {
      "message_id": 6207,
      "text": "Raid\n\nhttps://x.com/beraatkaratepe/status/2028369566489887060?s=46",
      "tweet_url": "https://x.com/i/web/status/2028369566489887060",
      "photo": "",
      "date": "2026-03-02T07:19:37Z",
      "chat_id": -1003708062172
    },
    {
      "message_id": 6205,
      "text": "",
      "tweet_url": "",
      "photo": "https://api.telegram.org/file/bot***REDACTED***/photos/file_3.jpg",
      "date": "2026-03-02T07:18:13Z",
      "chat_id": -1003708062172
    },
    {
      "message_id": 6204,
      "text": "Raid\n\nhttps://x.com/harrodfrances/status/2028369009184281079?s=46",
      "tweet_url": "https://x.com/i/web/status/2028369009184281079",
      "photo": "",
      "date": "2026-03-02T07:17:23Z",
      "chat_id": -1003708062172
    },
    {
      "message_id": 6202,
      "text": "Raid\n\nhttps://x.com/dedenovitaj/status/2028367101187203522?s=46",
      "tweet_url": "https://x.com/i/web/status/2028367101187203522",
      "photo": "",
      "date": "2026-03-02T07:09:45Z",
      "chat_id": -1003708062172
    },
    {
      "message_id": 6201,
      "text": "Raid\n\nhttps://x.com/harrodfrances/status/2028366907141697952?s=46",
      "tweet_url": "https://x.com/i/web/status/2028366907141697952",
      "photo": "",
      "date": "2026-03-02T07:09:00Z",
      "chat_id": -1003708062172
    },
    {
      "message_id": 6197,
      "text": "Raid\n\nhttps://coinmarketcap.com/community/share/post/374187807",
      "tweet_url": "",
      "photo": "",
      "date": "2026-03-02T06:19:19Z",
      "chat_id": -1003708062172
    },
    {
      "message_id": 6194,
      "text": "Good morning",
      "tweet_url": "",
      "photo": "",
      "date": "2026-03-02T06:10:52Z",
      "chat_id": -1003708062172
    },
    {
      "message_id": 6188,
      "text": "GM",
      "tweet_url": "",
      "photo": "",
      "date": "2026-03-02T05:32:08Z",
      "chat_id": -1003708062172
    },
    {
      "message_id": 6187,
      "text": "Raid \n\nhttps://x.com/i/status/2028342398762291373",
      "tweet_url": "https://x.com/i/web/status/2028342398762291373",
      "photo": "",
      "date": "2026-03-02T05:32:06Z",
      "chat_id": -1003708062172
    },
    {
      "message_id": 6186,
      "text": "Raid \n\nhttps://x.com/i/status/2028341436572172326",
      "tweet_url": "https://x.com/i/web/status/2028341436572172326",
      "photo": "",
      "date": "2026-03-02T05:32:02Z",
      "chat_id": -1003708062172
    },
    {
      "message_id": 6185,
      "text": "Raid \n\nhttps://x.com/i/status/2028339805772300332",
      "tweet_url": "https://x.com/i/web/status/2028339805772300332",
      "photo": "",
      "date": "2026-03-02T05:23:49Z",
      "chat_id": -1003708062172
    },
    {
      "message_id": 6184,
      "text": "Raid \n\nhttps://x.com/i/status/2028340027550212351",
      "tweet_url": "https://x.com/i/web/status/2028340027550212351",
      "photo": "",
      "date": "2026-03-02T05:23:46Z",
      "chat_id": -1003708062172
    },
    {
      "message_id": 6183,
      "text": "Raid \n\nhttps://x.com/i/status/2028340313694044521",
      "tweet_url": "https://x.com/i/web/status/2028340313694044521",
      "photo": "",
      "date": "2026-03-02T05:23:42Z",
      "chat_id": -1003708062172
    },
    {
      "message_id": 6181,
      "text": "Raid \n\nhttps://x.com/i/status/2028338678347530425",
      "tweet_url": "https://x.com/i/web/status/2028338678347530425",
      "photo": "",
      "date": "2026-03-02T05:18:22Z",
      "chat_id": -1003708062172
    },
    {
      "message_id": 6180,
      "text": "Raid \n\nhttps://x.com/i/status/2028339037082161642",
      "tweet_url": "https://x.com/i/web/status/2028339037082161642",
      "photo": "",
      "date": "2026-03-02T05:18:19Z",
      "chat_id": -1003708062172
    },
    {
      "message_id": 6162,
      "text": "https://x.com/i/status/2028137116018831717",
      "tweet_url": "https://x.com/i/web/status/2028137116018831717",
      "photo": "",
      "date": "2026-03-02T03:37:05Z",
      "chat_id": -1003708062172
    },
    {
      "message_id": 6145,
      "text": "https://x.com/i/status/2028168133798961395",
      "tweet_url": "https://x.com/i/web/status/2028168133798961395",
      "photo": "",
      "date": "2026-03-02T02:09:34Z",
      "chat_id": -1003708062172
    },
    {
      "message_id": 6135,
      "text": "https://x.com/no0blette/status/2028280776702251181?s=46",
      "tweet_url": "https://x.com/i/web/status/2028280776702251181",
      "photo": "",
      "date": "2026-03-02T01:28:55Z",
      "chat_id": -1003708062172
    },
    {
      "message_id": 6110,
      "text": "https://x.com/aytuggkuscuu/status/2028229797839811042?s=46",
      "tweet_url": "https://x.com/i/web/status/2028229797839811042",
      "photo": "",
      "date": "2026-03-01T22:04:51Z",
      "chat_id": -1003708062172
    },
    {
      "message_id": 6109,
      "text": "@oscarbrencyrpto @llVillainll @lenanacountter",
      "tweet_url": "",
      "photo": "",
      "date": "2026-03-01T21:53:26Z",
      "chat_id": -1003708062172
    },
    {
      "message_id": 6108,
      "text": "https://x.com/sushiswap/status/2028226662446620837?s=46",
      "tweet_url": "https://x.com/i/web/status/2028226662446620837",
      "photo": "",
      "date": "2026-03-01T21:52:50Z",
      "chat_id": -1003708062172
    },
    {
      "message_id": 6107,
      "text": "Raid \n\nhttps://x.com/i/status/2028226844152004609",
      "tweet_url": "https://x.com/i/web/status/2028226844152004609",
      "photo": "",
      "date": "2026-03-01T21:52:46Z",
      "chat_id": -1003708062172
    },
    {
      "message_id": 6106,
      "text": "Raid \n\nhttps://x.com/i/status/2028226629550419977",
      "tweet_url": "https://x.com/i/web/status/2028226629550419977",
      "photo": "",
      "date": "2026-03-01T21:52:42Z",
      "chat_id": -1003708062172
    },
    {
      "message_id": 6105,
      "text": "Raid \n\nhttps://x.com/i/status/2028225840484425929",
      "tweet_url": "https://x.com/i/web/status/2028225840484425929",
      "photo": "",
      "date": "2026-03-01T21:50:24Z",
      "chat_id": -1003708062172
    },
    {
      "message_id": 6104,
      "text": "Raid \n\nhttps://x.com/i/status/2028226228004569296",
      "tweet_url": "https://x.com/i/web/status/2028226228004569296",
      "photo": "",
      "date": "2026-03-01T21:50:17Z",
      "chat_id": -1003708062172
    },
    {
      "message_id": 6100,
      "text": "Raid\n\nhttps://x.com/davidmozsar/status/2028215620589047826?s=46",
      "tweet_url": "https://x.com/i/web/status/2028215620589047826",
      "photo": "",
      "date": "2026-03-01T21:07:48Z",
      "chat_id": -1003708062172
    },
    {
      "message_id": 6099,
      "text": "Raid\n\nhttps://x.com/dedenovitaj/status/2028215488426205402?s=46",
      "tweet_url": "https://x.com/i/web/status/2028215488426205402",
      "photo": "",
      "date": "2026-03-01T21:07:18Z",
      "chat_id": -1003708062172
    },
    {
      "message_id": 6098,
      "text": "Raid\n\nhttps://x.com/harrodfrances/status/2028215318892442004?s=46",
      "tweet_url": "https://x.com/i/web/status/2028215318892442004",
      "photo": "",
      "date": "2026-03-01T21:06:35Z",
      "chat_id": -1003708062172
    },
    {
      "message_id": 6097,
      "text": "Raid\n\nhttps://x.com/harrodfrances/status/2028214984015044778?s=46",
      "tweet_url": "https://x.com/i/web/status/2028214984015044778",
      "photo": "",
      "date": "2026-03-01T21:05:21Z",
      "chat_id": -1003708062172
    },
    {
      "message_id": 6096,
      "text": "Raid\n\nhttps://x.com/harrodfrances/status/2028214204117746079?s=46",
      "tweet_url": "https://x.com/i/web/status/2028214204117746079",
      "photo": "",
      "date": "2026-03-01T21:02:11Z",
      "chat_id": -1003708062172
    },
    {
      "message_id": 6094,
      "text": "https://x.com/aytuggkuscuu/status/2028213988878696853?s=46",
      "tweet_url": "https://x.com/i/web/status/2028213988878696853",
      "photo": "",
      "date": "2026-03-01T21:01:28Z",
      "chat_id": -1003708062172
    },
    {
      "message_id": 6093,
      "text": "Raid\n\nhttps://x.com/jasonredsheep/status/2028213773350171099?s=46",
      "tweet_url": "https://x.com/i/web/status/2028213773350171099",
      "photo": "",
      "date": "2026-03-01T21:00:35Z",
      "chat_id": -1003708062172
    },
    {
      "message_id": 6084,
      "text": "Raid\n\nhttps://x.com/dedenovitaj/status/2028206172566618603?s=46",
      "tweet_url": "https://x.com/i/web/status/2028206172566618603",
      "photo": "",
      "date": "2026-03-01T20:30:15Z",
      "chat_id": -1003708062172
    },
    {
      "message_id": 6083,
      "text": "Raid\n\nhttps://x.com/harrodfrances/status/2028206016987295842?s=46",
      "tweet_url": "https://x.com/i/web/status/2028206016987295842",
      "photo": "",
      "date": "2026-03-01T20:29:45Z",
      "chat_id": -1003708062172
    },
    {
      "message_id": 6058,
      "text": "Raid\n\nhttps://x.com/harrodfrances/status/2028183707845083540?s=46",
      "tweet_url": "https://x.com/i/web/status/2028183707845083540",
      "photo": "",
      "date": "2026-03-01T19:01:02Z",
      "chat_id": -1003708062172
    },
    {
      "message_id": 6046,
      "text": "Raid\n\nhttps://x.com/davidmozsar/status/2028173599291417009?s=46",
      "tweet_url": "https://x.com/i/web/status/2028173599291417009",
      "photo": "",
      "date": "2026-03-01T18:20:51Z",
      "chat_id": -1003708062172
    },
    {
      "message_id": 6045,
      "text": "Raid\n\nhttps://x.com/harrodfrances/status/2028173392604537184?s=46",
      "tweet_url": "https://x.com/i/web/status/2028173392604537184",
      "photo": "",
      "date": "2026-03-01T18:20:00Z",
      "chat_id": -1003708062172
    },
    {
      "message_id": 6035,
      "text": "Raid \n\nhttps://x.com/i/status/2028163964471783699",
      "tweet_url": "https://x.com/i/web/status/2028163964471783699",
      "photo": "",
      "date": "2026-03-01T17:51:43Z",
      "chat_id": -1003708062172
    },
    {
      "message_id": 6034,
      "text": "Raid \n\nhttps://x.com/i/status/2028165878370443588",
      "tweet_url": "https://x.com/i/web/status/2028165878370443588",
      "photo": "",
      "date": "2026-03-01T17:51:24Z",
      "chat_id": -1003708062172
    },
    {
      "message_id": 6033,
      "text": "Raid \n\nhttps://x.com/i/status/2028163102840164717",
      "tweet_url": "https://x.com/i/web/status/2028163102840164717",
      "photo": "",
      "date": "2026-03-01T17:51:21Z",
      "chat_id": -1003708062172
    },
    {
      "message_id": 6032,
      "text": "Raid \n\nhttps://x.com/i/status/2028164830616494221",
      "tweet_url": "https://x.com/i/web/status/2028164830616494221",
      "photo": "",
      "date": "2026-03-01T17:51:16Z",
      "chat_id": -1003708062172
    },
    {
      "message_id": 6031,
      "text": "Raid \n\nhttps://x.com/i/status/2028165146518982736",
      "tweet_url": "https://x.com/i/web/status/2028165146518982736",
      "photo": "",
      "date": "2026-03-01T17:51:13Z",
      "chat_id": -1003708062172
    },
    {
      "message_id": 6027,
      "text": "Raid\n\nhttps://x.com/beraatkaratepe/status/2028163126860882097?s=46",
      "tweet_url": "https://x.com/i/web/status/2028163126860882097",
      "photo": "",
      "date": "2026-03-01T17:39:15Z",
      "chat_id": -1003708062172
    },
    {
      "message_id": 6025,
      "text": "Raid\n\nhttps://x.com/davidmozsar/status/2028162963203379333?s=46",
      "tweet_url": "https://x.com/i/web/status/2028162963203379333",
      "photo": "",
      "date": "2026-03-01T17:38:33Z",
      "chat_id": -1003708062172
    },
    {
      "message_id": 6024,
      "text": "Raid\n\nhttps://x.com/harrodfrances/status/2028162742419325037?s=46",
      "tweet_url": "https://x.com/i/web/status/2028162742419325037",
      "photo": "",
      "date": "2026-03-01T17:37:42Z",
      "chat_id": -1003708062172
    },
    {
      "message_id": 6023,
      "text": "Raid\n\nhttps://x.com/dedenovitaj/status/2028162476194369573?s=46",
      "tweet_url": "https://x.com/i/web/status/2028162476194369573",
      "photo": "",
      "date": "2026-03-01T17:36:38Z",
      "chat_id": -1003708062172
    },
    {
      "message_id": 6022,
      "text": "https://x.com/67coinx/status/2028162231524073982?s=46",
      "tweet_url": "https://x.com/i/web/status/2028162231524073982",
      "photo": "",
      "date": "2026-03-01T17:35:54Z",
      "chat_id": -1003708062172
    },
    {
      "message_id": 6021,
      "text": "Raid \n\nhttps://x.com/i/status/2028162173243933041",
      "tweet_url": "https://x.com/i/web/status/2028162173243933041",
      "photo": "",
      "date": "2026-03-01T17:35:51Z",
      "chat_id": -1003708062172
    },
    {
      "message_id": 6020,
      "text": "Raid \n\nhttps://x.com/i/status/2028161025195827375",
      "tweet_url": "https://x.com/i/web/status/2028161025195827375",
      "photo": "",
      "date": "2026-03-01T17:35:45Z",
      "chat_id": -1003708062172
    },
    {
      "message_id": 6019,
      "text": "Raid \n\nhttps://x.com/i/status/2028161657193509094",
      "tweet_url": "https://x.com/i/web/status/2028161657193509094",
      "photo": "",
      "date": "2026-03-01T17:35:41Z",
      "chat_id": -1003708062172
    },
    {
      "message_id": 6015,
      "text": "Raid\n\nhttps://x.com/dedenovitaj/status/2028158011890377104?s=46",
      "tweet_url": "https://x.com/i/web/status/2028158011890377104",
      "photo": "",
      "date": "2026-03-01T17:18:55Z",
      "chat_id": -1003708062172
    },
    {
      "message_id": 6004,
      "text": "Raid\n\nhttps://x.com/beraatkaratepe/status/2028144647177228632?s=46",
      "tweet_url": "https://x.com/i/web/status/2028144647177228632",
      "photo": "",
      "date": "2026-03-01T16:25:49Z",
      "chat_id": -1003708062172
    },
    {
      "message_id": 6003,
      "text": "Raid\n\nhttps://x.com/davidmozsar/status/2028144521960202438?s=46",
      "tweet_url": "https://x.com/i/web/status/2028144521960202438",
      "photo": "",
      "date": "2026-03-01T16:25:17Z",
      "chat_id": -1003708062172
    },
    {
      "message_id": 6002,
      "text": "Raid\n\nhttps://x.com/dedenovitaj/status/2028144365898543536?s=46",
      "tweet_url": "https://x.com/i/web/status/2028144365898543536",
      "photo": "",
      "date": "2026-03-01T16:24:39Z",
      "chat_id": -1003708062172
    },
    {
      "message_id": 6001,
      "text": "Raid\n\nhttps://x.com/harrodfrances/status/2028144228472066550?s=46",
      "tweet_url": "https://x.com/i/web/status/2028144228472066550",
      "photo": "",
      "date": "2026-03-01T16:24:07Z",
      "chat_id": -1003708062172
    },
    {
      "message_id": 5992,
      "text": "https://x.com/christi35048051/status/2028138466744184979?s=46",
      "tweet_url": "https://x.com/i/web/status/2028138466744184979",
      "photo": "",
      "date": "2026-03-01T16:01:41Z",
      "chat_id": -1003708062172
    },
    {
      "message_id": 5990,
      "text": "Raid\n\nhttps://x.com/beraatkaratepe/status/2028135150979088492?s=46",
      "tweet_url": "https://x.com/i/web/status/2028135150979088492",
      "photo": "",
      "date": "2026-03-01T15:48:05Z",
      "chat_id": -1003708062172
    },
    {
      "message_id": 5989,
      "text": "Raid \n\nhttps://x.com/i/status/2028134177065886104",
      "tweet_url": "https://x.com/i/web/status/2028134177065886104",
      "photo": "",
      "date": "2026-03-01T15:48:02Z",
      "chat_id": -1003708062172
    },
    {
      "message_id": 5988,
      "text": "Raid \n\nhttps://x.com/i/status/2028134876637970502",
      "tweet_url": "https://x.com/i/web/status/2028134876637970502",
      "photo": "",
      "date": "2026-03-01T15:47:53Z",
      "chat_id": -1003708062172
    },
    {
      "message_id": 5987,
      "text": "Raid \n\nhttps://x.com/i/status/2028133947889029609",
      "tweet_url": "https://x.com/i/web/status/2028133947889029609",
      "photo": "",
      "date": "2026-03-01T15:47:50Z",
      "chat_id": -1003708062172
    },
    {
      "message_id": 5986,
      "text": "Raid \n\nhttps://x.com/i/status/2028134506792710392",
      "tweet_url": "https://x.com/i/web/status/2028134506792710392",
      "photo": "",
      "date": "2026-03-01T15:47:47Z",
      "chat_id": -1003708062172
    },
    {
      "message_id": 5985,
      "text": "Raid \n\nhttps://x.com/i/status/2028132204820189275",
      "tweet_url": "https://x.com/i/web/status/2028132204820189275",
      "photo": "",
      "date": "2026-03-01T15:47:44Z",
      "chat_id": -1003708062172
    },
    {
      "message_id": 5979,
      "text": "https://x.com/no0blette/status/2028124022228037962?s=46\n\n@llVillainll @veracrosss @lenanacountter",
      "tweet_url": "https://x.com/i/web/status/2028124022228037962",
      "photo": "",
      "date": "2026-03-01T15:31:04Z",
      "chat_id": -1003708062172
    },
    {
      "message_id": 5964,
      "text": "Raid \n\nhttps://x.com/i/status/2028118956876112181",
      "tweet_url": "https://x.com/i/web/status/2028118956876112181",
      "photo": "",
      "date": "2026-03-01T14:43:57Z",
      "chat_id": -1003708062172
    },
    {
      "message_id": 5960,
      "text": "Raid\n\nhttps://x.com/davidmozsar/status/2028113818597912886?s=46",
      "tweet_url": "https://x.com/i/web/status/2028113818597912886",
      "photo": "",
      "date": "2026-03-01T14:23:21Z",
      "chat_id": -1003708062172
    },
    {
      "message_id": 5958,
      "text": "Raid\n\nhttps://x.com/belleselbe/status/2028111497948201084?s=46",
      "tweet_url": "https://x.com/i/web/status/2028111497948201084",
      "photo": "",
      "date": "2026-03-01T14:14:28Z",
      "chat_id": -1003708062172
    },
    {
      "message_id": 5957,
      "text": "Raid\n\nhttps://x.com/belleselbe/status/2028097469708415239?s=46",
      "tweet_url": "https://x.com/i/web/status/2028097469708415239",
      "photo": "",
      "date": "2026-03-01T14:14:27Z",
      "chat_id": -1003708062172
    },
    {
      "message_id": 5950,
      "text": "Raid \n\nhttps://x.com/i/status/2028094933765063079",
      "tweet_url": "https://x.com/i/web/status/2028094933765063079",
      "photo": "",
      "date": "2026-03-01T13:15:13Z",
      "chat_id": -1003708062172
    },
    {
      "message_id": 5949,
      "text": "Raid \n\nhttps://x.com/i/status/2028095305548247152",
      "tweet_url": "https://x.com/i/web/status/2028095305548247152",
      "photo": "",
      "date": "2026-03-01T13:15:10Z",
      "chat_id": -1003708062172
    },
    {
      "message_id": 5948,
      "text": "Raid \n\nhttps://x.com/i/status/2028096523133763807",
      "tweet_url": "https://x.com/i/web/status/2028096523133763807",
      "photo": "",
      "date": "2026-03-01T13:14:57Z",
      "chat_id": -1003708062172
    },
    {
      "message_id": 5947,
      "text": "Raid \n\nhttps://x.com/i/status/2028094325238739294",
      "tweet_url": "https://x.com/i/web/status/2028094325238739294",
      "photo": "",
      "date": "2026-03-01T13:14:54Z",
      "chat_id": -1003708062172
    },
    {
      "message_id": 5946,
      "text": "Raid \n\nhttps://x.com/i/status/2028096077702762570",
      "tweet_url": "https://x.com/i/web/status/2028096077702762570",
      "photo": "",
      "date": "2026-03-01T13:14:51Z",
      "chat_id": -1003708062172
    },
    {
      "message_id": 5945,
      "text": "Raid \n\nhttps://x.com/i/status/2028094597482598665",
      "tweet_url": "https://x.com/i/web/status/2028094597482598665",
      "photo": "",
      "date": "2026-03-01T13:14:48Z",
      "chat_id": -1003708062172
    },
    {
      "message_id": 5943,
      "text": "Raid\n\nhttps://x.com/beraatkaratepe/status/2028094048825672017?s=46",
      "tweet_url": "https://x.com/i/web/status/2028094048825672017",
      "photo": "",
      "date": "2026-03-01T13:04:46Z",
      "chat_id": -1003708062172
    },
    {
      "message_id": 5942,
      "text": "Raid\n\nhttps://x.com/davidmozsar/status/2028093830008811852?s=46",
      "tweet_url": "https://x.com/i/web/status/2028093830008811852",
      "photo": "",
      "date": "2026-03-01T13:03:54Z",
      "chat_id": -1003708062172
    },
    {
      "message_id": 5941,
      "text": "Raid\n\nhttps://x.com/dedenovitaj/status/2028093683950600472?s=46",
      "tweet_url": "https://x.com/i/web/status/2028093683950600472",
      "photo": "",
      "date": "2026-03-01T13:03:17Z",
      "chat_id": -1003708062172
    },
    {
      "message_id": 5940,
      "text": "Raid\n\nhttps://x.com/harrodfrances/status/2028093504505692278?s=46",
      "tweet_url": "https://x.com/i/web/status/2028093504505692278",
      "photo": "",
      "date": "2026-03-01T13:02:36Z",
      "chat_id": -1003708062172
    },
    {
      "message_id": 5938,
      "text": "https://x.com/67coinX/status/2028091411988394174",
      "tweet_url": "https://x.com/i/web/status/2028091411988394174",
      "photo": "",
      "date": "2026-03-01T12:59:42Z",
      "chat_id": -1003708062172
    },
    {
      "message_id": 5935,
      "text": "Raid\n\nhttps://x.com/harrodfrances/status/2028091158111420765?s=46",
      "tweet_url": "https://x.com/i/web/status/2028091158111420765",
      "photo": "",
      "date": "2026-03-01T12:53:16Z",
      "chat_id": -1003708062172
    },
    {
      "message_id": 5929,
      "text": "",
      "tweet_url": "",
      "photo": "https://api.telegram.org/file/bot***REDACTED***/photos/file_2.jpg",
      "date": "2026-03-01T12:24:38Z",
      "chat_id": -1003708062172
    },
    {
      "message_id": 5928,
      "text": "",
      "tweet_url": "",
      "photo": "https://api.telegram.org/file/bot***REDACTED***/photos/file_1.jpg",
      "date": "2026-03-01T12:24:34Z",
      "chat_id": -1003708062172
    },
    {
      "message_id": 5927,
      "text": "Raid\n\nhttps://x.com/beraatkaratepe/status/2028083746574946518?s=46",
      "tweet_url": "https://x.com/i/web/status/2028083746574946518",
      "photo": "",
      "date": "2026-03-01T12:23:49Z",
      "chat_id": -1003708062172
    },
    {
      "message_id": 5912,
      "text": "Raid\n\nhttps://x.com/dedenovitaj/status/2028066003540668455?s=46",
      "tweet_url": "https://x.com/i/web/status/2028066003540668455",
      "photo": "",
      "date": "2026-03-01T11:13:17Z",
      "chat_id": -1003708062172
    },
    {
      "message_id": 5911,
      "text": "Raid\n\nhttps://x.com/harrodfrances/status/2028065829237993807?s=46",
      "tweet_url": "https://x.com/i/web/status/2028065829237993807",
      "photo": "",
      "date": "2026-03-01T11:12:37Z",
      "chat_id": -1003708062172
    },
    {
      "message_id": 5910,
      "text": "Raid \n\nhttps://x.com/i/status/2028064226036601193",
      "tweet_url": "https://x.com/i/web/status/2028064226036601193",
      "photo": "",
      "date": "2026-03-01T11:06:45Z",
      "chat_id": -1003708062172
    },
    {
      "message_id": 5907,
      "text": "Raid\n\nhttps://coinmarketcap.com/community/share/post/374173295",
      "tweet_url": "",
      "photo": "",
      "date": "2026-03-01T10:40:05Z",
      "chat_id": -1003708062172
    },
    {
      "message_id": 5890,
      "text": "Raid \n\nhttps://x.com/i/status/2028012454362391025",
      "tweet_url": "https://x.com/i/web/status/2028012454362391025",
      "photo": "",
      "date": "2026-03-01T07:40:47Z",
      "chat_id": -1003708062172
    },
    {
      "message_id": 5889,
      "text": "Raid \n\nhttps://x.com/i/status/2028011898348744991",
      "tweet_url": "https://x.com/i/web/status/2028011898348744991",
      "photo": "",
      "date": "2026-03-01T07:38:47Z",
      "chat_id": -1003708062172
    }
  ],
  "x_recent": [
    {
      "id": "2032582475357004049",
      "user": "GSAthletics_BSB",
      "text": "Work to do after 6.\n\nTop 7: GS 4 | JMU 12\n\n#HailSouthern",
      "likes": 0,
      "reposts": 0,
      "replies": 0,
      "time": "Fri Mar 13 22:20:00 +0000 2026",
      "link": "https://x.com/GSAthletics_BSB/status/2032582475357004049",
      "tag": "6/7"
    },
    {
      "id": "2032582472756511091",
      "user": "OHLSteelheads",
      "text": "\ud83d\udc40 Starting lineup and projected lines for tonight\u2019s MS Awareness Game vs the Ottawa 67's, brought to you by @SmartStopSS! \ud83d\udc99\ud83d\udc1f https://t.co/Q7Og7gUWOY",
      "likes": 0,
      "reposts": 0,
      "replies": 0,
      "time": "Fri Mar 13 22:19:59 +0000 2026",
      "link": "https://x.com/OHLSteelheads/status/2032582472756511091",
      "tag": "$67"
    },
    {
      "id": "2032582472551350682",
      "user": "nwishy1",
      "text": "\u0641\u064a \u062d\u0631\u0628 56 \u0625\u0628\u0627\u0646 #\u0627\u0644\u0639\u062f\u0648\u0627\u0646_\u0627\u0644\u062b\u0644\u0627\u062b\u064a \u0644\u0645 \u062a\u0642\u0644 #\u0627\u0644\u0633\u0639\u0648\u062f\u064a\u0629 \u0623\u0646\u0647\u0627 \u0645\u0633\u062a\u0639\u062f\u0629 \u0644\u0644\u0648\u0633\u0627\u0637\u0629 \u0628\u0644 \u0642\u0637\u0639\u062a #\u0627\u0644\u0646\u0641\u0637 \u0648\u0644\u0645 \u064a\u0643\u0646 \u0627\u0644\u0648\u0636\u0639 \u0627\u0644\u0627\u0642\u062a\u0635\u0627\u062f\u064a \u0643\u0645\u0627 \u0647\u0648 \u0639\u0644\u064a\u0647 \u0627\u0644\u064a\u0648\u0645 \u0648\u0644\u0644\u0647 \u0627\u0644\u062d\u0645\u062f \u0648\u0627\u0644\u0645\u0646\u0629 \u060c \u0648\u0644\u0643\u0646\u0647\u0627 \u0639\u0642\u064a\u062f\u0629 \u0627\u0644\u062a\u0648\u062d\u064a\u062f \u0648\u0646\u062e\u0648\u0629 #\u0627\u0644\u0639\u0631\u0628\u064a #\u0627\u0644\u0628\u062f\u0648\u064a \u0627\u0644\u0623\u0635\u064a\u0644\n\u0648\u0643\u0630\u0644\u0643 \u0641\u064a \u062d\u0631\u0648\u0628 67 \u0648 73 \u0648\u0645\u0627\u0628\u064a\u0646\u0647\u0645\u0627 \u0648\u0641\u0648\u0636\u0649 #\u0627\u0644\u0631\u0628\u064a\u0639_\u0627\u0644\u0639\u0631\u0628\u064a \u0644\u0645 \u0646\u0642\u0644 \u0645\u0633\u062a\u0639\u062f\u0648\u0646 \u0644\u0644\u0648\u0633\u0627\u0637\u0629 \u0628\u0644 \u0643\u0627\u0646\u062a",
      "likes": 0,
      "reposts": 0,
      "replies": 0,
      "time": "Fri Mar 13 22:19:59 +0000 2026",
      "link": "https://x.com/nwishy1/status/2032582472551350682",
      "tag": "$67"
    },
    {
      "id": "2032582469615071273",
      "user": "CassMac_21",
      "text": "Braves beat Yankees 7-6 Fuentes electric again! Dub\u00f3n homers Farmer big day #BravesCountry https://t.co/5sSQvU3FRc",
      "likes": 0,
      "reposts": 0,
      "replies": 0,
      "time": "Fri Mar 13 22:19:58 +0000 2026",
      "link": "https://x.com/CassMac_21/status/2032582469615071273",
      "tag": "6/7"
    },
    {
      "id": "2032582461327347897",
      "user": "WZ_0125",
      "text": "\u8ddf\u670b\u53cb\u4e00\u8d77\u62bd&amp;TEAM\u5de1\u8ff4\n\u7d50\u679c\u62bd\u52306/28\u5175\u5eab\n\u4f467/4\u30015\u8981\u5728\u6a6b\u6ff1\u770bAdo\u53ea\u597d\u5fcd\u75db\u5272\u611b\u22ef\u22ef",
      "likes": 1,
      "reposts": 0,
      "replies": 1,
      "time": "Fri Mar 13 22:19:56 +0000 2026",
      "link": "https://x.com/WZ_0125/status/2032582461327347897",
      "tag": "6/7"
    },
    {
      "id": "2032582456046415880",
      "user": "josh_zbrakr",
      "text": "Anyone interested in my Three tickets for Big 12 Mens Basketball Tournament - Session 7 - Houston vs Kansas Game tonight \n\n@ The T-Mobile Center - Kansas City, MO\nTime: 6:00pm\n\nMessage me if you\u2019re interested \u2764\ufe0f\ud83d\ude4f\nAsking for $125 each per ticket \ud83c\udfab https://t.co/D5YvQOp32n",
      "likes": 0,
      "reposts": 0,
      "replies": 0,
      "time": "Fri Mar 13 22:19:55 +0000 2026",
      "link": "https://x.com/josh_zbrakr/status/2032582456046415880",
      "tag": "6/7"
    },
    {
      "id": "2032582450904261038",
      "user": "dannymiche",
      "text": "Gan\u00f3 Mariano Navone 6/2 y 7/6(5) a Valentin Royer y es semifinalista en el Challenger de Cap Cana \nMa\u00f1ana va contra el belga Alexander Blockx https://t.co/tEl8emzRK3",
      "likes": 0,
      "reposts": 0,
      "replies": 0,
      "time": "Fri Mar 13 22:19:54 +0000 2026",
      "link": "https://x.com/dannymiche/status/2032582450904261038",
      "tag": "6/7"
    },
    {
      "id": "2032582448446603397",
      "user": "ja_yubari",
      "text": "\u304a\u306f\u3088\uff01\n\u671d\u65e9\u3044\u304b\u3089\u8eca\u3044\u306a\u3044\u306d(*\u00b4-`)\n\n\u26ab\ufe0f\u5915\u5f35\u5e02\u3000\u6625\u304c\u6765\u305d\u3046\u306a\u8857\u3000\u6c17\u6e29-1\u2103\n\ud83d\udfe0\u30e1\u30ed\u30f3\u53ce\u7a6b\u307e\u3067\u3000\u3042\u306867\u65e5\u304f\u3089\u3044\n\u26aa\ufe0f\u5915\u5f35\u30e1\u30ed\u30f3\u30aa\u30d5\u4f1a\u3000\u3042\u3068130\u65e5\u3014\u76ee\u6a19\u3015\n\ud83d\udd34\u5915\u5f35\u7523\u30c8\u30de\u30c8\u30bd\u30fc\u30b9\u5b8c\u6210 209\u65e5\u3014\u76ee\u6a19\u3015 https://t.co/TH0LY5cD8k",
      "likes": 0,
      "reposts": 0,
      "replies": 0,
      "time": "Fri Mar 13 22:19:53 +0000 2026",
      "link": "https://x.com/ja_yubari/status/2032582448446603397",
      "tag": "$67"
    },
    {
      "id": "2032582438136750255",
      "user": "PatoGuerra10",
      "text": "@patriota_1972 @maripos04716945 @realDonaldTrump A  Ojal\u00e1, por su gente no se merecen 67 a\u00f1os d\u00e9 esclavitud",
      "likes": 0,
      "reposts": 0,
      "replies": 0,
      "time": "Fri Mar 13 22:19:51 +0000 2026",
      "link": "https://x.com/PatoGuerra10/status/2032582438136750255",
      "tag": "67"
    },
    {
      "id": "2032582438644269228",
      "user": "vt7io",
      "text": "@Calcio_223 \u0648\u0648\u0644 \u064a\u0627\u0644\u062d\u0646\u0643\u0629",
      "likes": 0,
      "reposts": 0,
      "replies": 0,
      "time": "Fri Mar 13 22:19:51 +0000 2026",
      "link": "https://x.com/vt7io/status/2032582438644269228",
      "tag": "$67"
    },
    {
      "id": "2032582411494506844",
      "user": "lindatwist55",
      "text": "@ShibraAwan 67 upside down",
      "likes": 0,
      "reposts": 0,
      "replies": 0,
      "time": "Fri Mar 13 22:19:45 +0000 2026",
      "link": "https://x.com/lindatwist55/status/2032582411494506844",
      "tag": "67"
    },
    {
      "id": "2032582408760078669",
      "user": "wcsFHSsb",
      "text": "\u2693\ufe0f LADY ADMIRALS WEDNESDAY RECAP \ud83e\udd4e\nFranklin battled through a full day of games and finished 3\u20131 on the day with clutch hitting and dominant pitching.  \n\nGame 1 \u2013 Franklin 7, Gallatin 6 (Walk-Off Win)\nFranklin battled back and won it in dramatic fashion when Adelynn Cherry https:",
      "likes": 0,
      "reposts": 0,
      "replies": 0,
      "time": "Fri Mar 13 22:19:44 +0000 2026",
      "link": "https://x.com/wcsFHSsb/status/2032582408760078669",
      "tag": "6/7"
    },
    {
      "id": "2032582390971761084",
      "user": "UnrivaledSpeed",
      "text": "Six or seven huh",
      "likes": 0,
      "reposts": 0,
      "replies": 0,
      "time": "Fri Mar 13 22:19:40 +0000 2026",
      "link": "https://x.com/UnrivaledSpeed/status/2032582390971761084",
      "tag": "Six Seven"
    },
    {
      "id": "2032582382600204743",
      "user": "timmyappstore",
      "text": "@bloomingcacies Yuuu lgsg invite\n\u2728CANVA \n\u2661Harian\n\u20221hari 3k\n\u20223 hari 5k\n\u20227 hari 7k\n\u2661 Member\n\u20221 bulan : 8k\n\u20222 bulan : 9k\n\u20223 bulan : 11k\n\u20226 bulan : 13k\n\u20221 tahun garansi 6b: 15k\n\u20221 tahun full garansi: 20k\n\u2022lifetime : 25k\nDesigner +2k",
      "likes": 0,
      "reposts": 0,
      "replies": 0,
      "time": "Fri Mar 13 22:19:38 +0000 2026",
      "link": "https://x.com/timmyappstore/status/2032582382600204743",
      "tag": "6/7"
    },
    {
      "id": "2032582372281987318",
      "user": "Keitha5511938",
      "text": "@MbarkCherguia 67",
      "likes": 0,
      "reposts": 0,
      "replies": 0,
      "time": "Fri Mar 13 22:19:35 +0000 2026",
      "link": "https://x.com/Keitha5511938/status/2032582372281987318",
      "tag": "67"
    },
    {
      "id": "2032582368490357175",
      "user": "CoachJzajac",
      "text": "@HurrdatSports 7-6 or 5-7",
      "likes": 0,
      "reposts": 0,
      "replies": 0,
      "time": "Fri Mar 13 22:19:34 +0000 2026",
      "link": "https://x.com/CoachJzajac/status/2032582368490357175",
      "tag": "6/7"
    },
    {
      "id": "2032582364501618887",
      "user": "lill365",
      "text": "#\u0633\u0628\u064a\u0633 67",
      "likes": 0,
      "reposts": 0,
      "replies": 0,
      "time": "Fri Mar 13 22:19:33 +0000 2026",
      "link": "https://x.com/lill365/status/2032582364501618887",
      "tag": "67"
    },
    {
      "id": "2032582356876537994",
      "user": "venombytte",
      "text": "no matter the outcome I can\u2019t really see myself saying \u201c6hypen\u201d or \u201cenhypen is 6\u201d ever, it doesn\u2019t compute. even if they successfully do separate things as enhypen and soloist heeseung (which I can support \ud83d\ude14) i will always see enhypen as a 7 member group https://t.co/bxEu5jbjE9",
      "likes": 0,
      "reposts": 0,
      "replies": 1,
      "time": "Fri Mar 13 22:19:32 +0000 2026",
      "link": "https://x.com/venombytte/status/2032582356876537994",
      "tag": "6/7"
    },
    {
      "id": "2032582352853950489",
      "user": "realGnatTserong",
      "text": "@MbarkCherguia Some say upside down 67, I also say without flipping the phone that it is a 9 degree angle, final answer\u2026lock it in! \ud83d\ude0e",
      "likes": 0,
      "reposts": 0,
      "replies": 0,
      "time": "Fri Mar 13 22:19:31 +0000 2026",
      "link": "https://x.com/realGnatTserong/status/2032582352853950489",
      "tag": "67"
    },
    {
      "id": "2032582352812257377",
      "user": "abba894",
      "text": "@Rota4152 \u304a\u306f\u3088\u3046\u3054\u3056\u3044\u307e\u3059\ud83e\udd70\u30db\u30bb\u30a2\u66f86:6\u306e\"\u79c1\u304c\u6c42\u3081\u308b\u306e\u306f\u6190\u308c\u307f\u3067\u3042\u3063\u3066\u3001\u3044\u3051\u306b\u3048\u3067\u306f\u306a\u3044\u3002\"\u306f\u3001\u30de\u30bf\u30a4\u798f\u97f3\u66f8\u3067\u306f9:13\u306812:7\u3067\u4e8c\u5ea6\u3082\u5f15\u7528\u3057\u3066\u3044\u307e\u3059\u3002\u4eba\u3092\u611b\u3059\u308b\u795e\u306e\u5fc3\u3092\u7406\u89e3\u305b\u3088\u3001\u3068\u3044\u3046\u3053\u3068\u3067\u3057\u3087\u3046\u304b\u3002\n\u6b8b\u5ff5\u306a\u304c\u3089\u98a8\u90aa\u3067\u30c0\u30a6\u30f3\ud83e\udd27\u3053\u308c\u304b\u3089\u307e\u305f\u5e03\u56e3\u3067\u5bdd\u307e\u3059\u3002\u826f\u3044\u9031\u672b\u3068\u306a\u308a\u307e\u3059\u3088\u3046\u306b\ud83d\ude4f\ud83d\ude4f\ud83d\ude4f",
      "likes": 0,
      "reposts": 0,
      "replies": 0,
      "time": "Fri Mar 13 22:19:31 +0000 2026",
      "link": "https://x.com/abba894/status/2032582352812257377",
      "tag": "6/7"
    },
    {
      "id": "2032582346998763561",
      "user": "KgKimmy63",
      "text": "@SpearsPatsy @DrBitcoinMD @tedcruz Deuteronomy 7:6\nESV\n\"For you are a people holy to the Lord your God. The Lord your God has chosen you to be a people for his treasured possession, out of all the peoples who are on the face of the earth. \n  Also, the Romans crucified Jesus.",
      "likes": 0,
      "reposts": 0,
      "replies": 0,
      "time": "Fri Mar 13 22:19:29 +0000 2026",
      "link": "https://x.com/KgKimmy63/status/2032582346998763561",
      "tag": "6/7"
    },
    {
      "id": "2032582344461398215",
      "user": "ginkoji",
      "text": "@takai_shin \u6885\u5730\u4e0b\u3092\u77e5\u3063\u305f\u306e\u306f\u9ad8\u6821\u751f\u306e\u6642\u3002\u5b66\u6821\u9055\u3044\u306e\u53cb\u4eba\u304b\u3089\u501f\u308a\u3066\u3001\u81ea\u5206\u3067\u3082\u6b32\u3057\u304f\u3066\u63a2\u3057\u305f\u306e\u306b\u3001\u305d\u306e\u6642\u306b\u306f\u4f8b\u306e\u4e8b\u4ef6\u3042\u304a\u308a\u3067\u7d76\u7248\u3068\u306a\u3063\u3066\u305forz\n6\u5e74\uff1f7\u5e74\uff1f\u5f8c\u3001\u77e5\u4eba\u304c\u5927\u962a\u306e\u53e4\u66f8\u5e97\u3067\u898b\u3064\u3051\u305f\u304b\u3089\u304a\u571f\u7523\uff01\u3063\u3066\n\u305d\u306e\u6642\u3001\u4eba\u3068\u672c\u306e\u9593\u306b\u7e01\u304c\u3042\u308c\u3070\u3001\u6642\u9593\u304c\u304b\u304b\u3063\u3066\u3082\u51fa\u4f1a\u3048\u308b\u306e\u3060\u3068\u601d\u3063\u305f\u51fa\u6765\u4e8b\u3067\u3059",
      "likes": 0,
      "reposts": 0,
      "replies": 0,
      "time": "Fri Mar 13 22:19:29 +0000 2026",
      "link": "https://x.com/ginkoji/status/2032582344461398215",
      "tag": "6/7"
    },
    {
      "id": "2032582341319655479",
      "user": "BlackBu10721816",
      "text": "@Twitercuen1114 @nazarubyjane Callate aweonao,la wea nunca fue as\u00ed,los Haitianos son retrasados con un IQ promedio de 67,esa calma que llamas es que su cerebro est\u00e1 en trance,si los sacas de este se vuelven violentos y por eso Hait\u00ed es el pa\u00eds m\u00e1s violento de am\u00e9rica.\nEsa gente c",
      "likes": 0,
      "reposts": 0,
      "replies": 0,
      "time": "Fri Mar 13 22:19:28 +0000 2026",
      "link": "https://x.com/BlackBu10721816/status/2032582341319655479",
      "tag": "67"
    },
    {
      "id": "2032582337117262267",
      "user": "emuraku",
      "text": "\uff13\uff12\u5104\uff16\uff16\uff19\uff15\u4e07\u5186\u30ad\u30e3\u30ea\u30fc\u30aa\u30fc\u30d0\u30fc\u4e2d\uff01\u30ed\u30c8\uff17\u306e\uff16\uff16\uff19\u56de(\u6771\u4eac\u62bd\u7c64)\u4e00\u53e3\u4e88\u60f3\uff01\u51fa\u76ee\u8868\u3092\u773a\u3081\u3066\u306e\u81ea\u529b\u9078\u51fa\uff5c\u30ed\u30c86\u3068\u30ed\u30c87\u306e\u4e88\u60f3 by M\u697d\u51fa\u6f6e @emuraku https://t.co/u8IkSntBFV",
      "likes": 0,
      "reposts": 0,
      "replies": 0,
      "time": "Fri Mar 13 22:19:27 +0000 2026",
      "link": "https://x.com/emuraku/status/2032582337117262267",
      "tag": "6/7"
    },
    {
      "id": "2032582332494794832",
      "user": "ku_weidmann",
      "text": "@maurerchr @PfeifferCarsten @BergheimJeff Gibt auch signifikante Unterschiede,\nEE:\n1. extrem modular\n2. extrem dezentral m\u00f6glich\n3. Technologief\u00fchrerschaft in D\n4. kein Brennstoff\n5. gro\u00dfe Akteursvielfalt horizontal + vertikal\n6. kurze Innovationszyklen\n7. kein Endlager\n8. kein h",
      "likes": 0,
      "reposts": 0,
      "replies": 0,
      "time": "Fri Mar 13 22:19:26 +0000 2026",
      "link": "https://x.com/ku_weidmann/status/2032582332494794832",
      "tag": "6/7"
    },
    {
      "id": "2032582331295584287",
      "user": "Trumpett3",
      "text": "G7 MEETING VOTE TO ALLOW US/TRUMP JOIN IN:\n\n1. CANADA, VOTE HELL NO!\n2. FRANCE, VOTE NO!\n3. GERMANY, VOTE NO! LOL\n4. ITALY, VOTE NO!\n5. JAPAN, VOTE NO!\n6. UK UNITED KINGDOM, VOTE NO!\n7. UNITED STATES, NOT ALLOWED TO VOTE\n8. RUSSIA, NOT ALLOWED TO VOTE\n\nTRUMP NOT INVITED TO ATTEND",
      "likes": 0,
      "reposts": 0,
      "replies": 0,
      "time": "Fri Mar 13 22:19:25 +0000 2026",
      "link": "https://x.com/Trumpett3/status/2032582331295584287",
      "tag": "6/7"
    },
    {
      "id": "2032582312693583919",
      "user": "joongspell",
      "text": "@hoonseasons @yjwxzq @HYBEOFFICIALtwt six\n\n@HYBEOFFICIALtwt\n \u30d2\u30b9\u30f3\u3092\u518d\u3073\u30a8\u30f3\u30cf\u30a4\u30d7\u30f3\u306b\u623b\u305b\uff01\n\n#\u30a8\u30f3\u30cf\u30a4\u30d5\u30f3\u306f_7\n#\u30a8\u30f3\u30cf\u30a4\u30d5\u30f3\u306f_7\u4eba\n#\u30a8\u30f3\u30cf\u30a4\u30d5\u30f3_\u4e03\u3092_\u5b88\u308c\n#\u30d3\u30ea\u30fc\u30d5\u30e9\u30c3\u30d6_\u8aac\u660e\u3057\u3066\u304f\u3060\u3055\u3044\n#PROTECT_ENHYPEN",
      "likes": 0,
      "reposts": 0,
      "replies": 0,
      "time": "Fri Mar 13 22:19:21 +0000 2026",
      "link": "https://x.com/joongspell/status/2032582312693583919",
      "tag": "Six Seven"
    },
    {
      "id": "2032582310810497330",
      "user": "yusei_nichijo",
      "text": "\u843d\u5358\u6253\u7dda\n1 (\u4e8c) \u8907\u7d20\u89e3\u6790\u5b66\u2190\u4f1d\u8aac9\u70b9\n2 (\u4e2d) \u5fdc\u7528\u89e3\u6790\u5b66\u2160\u2190\u5fc5\u4fee\n3 (\u5de6) \u5236\u5fa1\u5de5\u5b66\u2160\u2190\u5fc5\u4fee\n4 (\u53f3) \u6a5f\u68b0\u529b\u5b66\u2160\u2190\u5fc5\u4fee\n5 (\u4e00) \u6a5f\u68b0\u8a2d\u8a08\u88fd\u56f3\u2160\u2190\u5fc5\u4fee\u3001\u304a\u60c5\u3051\n6 (\u4e09) \u4ee3\u6570\u5b66\u2161\u2190\u518d\u5c65\u3001\u304a\u60c5\u3051\n7 (\u6355) \u529b\u5b66\u2160\u2190\u518d\u5c65\u3001\u5fc5\u4fee\u3001\u304a\u60c5\u3051\n8 (\u904a) \u6750\u6599\u529b\u5b66\u2160\u2190\u4e2d\u9593\u8ffd\u8a66\n9 (\u6295) \u57fa\u790e\u6750\u6599\u5de5\u5b66\u2160\u2190\u8a66\u9a13\u8ffd\u3005\u8a66\u3001\u304a\u60c5\u3051",
      "likes": 0,
      "reposts": 0,
      "replies": 0,
      "time": "Fri Mar 13 22:19:21 +0000 2026",
      "link": "https://x.com/yusei_nichijo/status/2032582310810497330",
      "tag": "6/7"
    },
    {
      "id": "2032582307362779201",
      "user": "Xtrullz",
      "text": "@PuppetCombo I love pt 7 design, movie would be better if they didn't get screwed over in the censorship department, but 6 is undoubtedly my favorite overall movie",
      "likes": 0,
      "reposts": 0,
      "replies": 0,
      "time": "Fri Mar 13 22:19:20 +0000 2026",
      "link": "https://x.com/Xtrullz/status/2032582307362779201",
      "tag": "6/7"
    },
    {
      "id": "2032582306301428084",
      "user": "get_sixtones",
      "text": "7:19\n\n\u300eSixTONES\u300f\u60c5\u5831\n\n\ud83d\udc8e\u30b8\u30a7\u30b7\u30fc\n\ud83d\udc8e\u4eac\u672c\u5927\u6211\n\ud83d\udc8e\u677e\u6751\u5317\u6597\n\ud83d\udc8e\u9ad9\u5730\u512a\u543e\n\ud83d\udc8e\u68ee\u672c\u614e\u592a\u90ce\n\ud83d\udc8e\u7530\u4e2d\u6a39\n\nJ-GENERATION 2024\u5e74 6\u6708\u53f7\u3010\u307e\u308b\u3054\u30681\u518a\u5927\u7279\u96c6!!\u3011 SixTONES as actors Vol.1...\n\n\u8a73\u7d30\u306f\u697d\u5929\u516c\u5f0f\u30b5\u30a4\u30c8\u3067\u2b07\n\nhttps://t.co/6hwzvaTlsU",
      "likes": 0,
      "reposts": 0,
      "replies": 0,
      "time": "Fri Mar 13 22:19:20 +0000 2026",
      "link": "https://x.com/get_sixtones/status/2032582306301428084",
      "tag": "6/7"
    },
    {
      "id": "2032582289293467749",
      "user": "grok",
      "text": "@NooRaaa99_ @NewsNow4USA Yes, it's real. German Chancellor Friedrich Merz said exactly that today at a press conference in Norway with PMs Carney (Canada) and St\u00f8re (Norway): 6/7 G7 countries opposed lifting Russia sanctions, surprised by the US decision, and want more pressure t",
      "likes": 0,
      "reposts": 0,
      "replies": 0,
      "time": "Fri Mar 13 22:19:15 +0000 2026",
      "link": "https://x.com/grok/status/2032582289293467749",
      "tag": "6/7"
    },
    {
      "id": "2032582284214145502",
      "user": "jmacho162",
      "text": "@HoP_Racing @JennaBAOtten @JRhein98 @gabe_prewitt Race 6) #7 Salty Robyn N  #PlayHP",
      "likes": 0,
      "reposts": 0,
      "replies": 0,
      "time": "Fri Mar 13 22:19:14 +0000 2026",
      "link": "https://x.com/jmacho162/status/2032582284214145502",
      "tag": "6/7"
    },
    {
      "id": "2032582235006570510",
      "user": "CAStolzenbach",
      "text": "\ud83c\udfc8 Immaculate Grid 968 9/9:\nRarity: 67\nIMMACULATE!\n\ud83d\udfe9\ud83d\udfe9\ud83d\udfe9\n\ud83d\udfe9\ud83d\udfe9\ud83d\udfe9\n\ud83d\udfe9\ud83d\udfe9\ud83d\udfe9\n\u27a1\ufe0f See my grid:\nhttps://t.co/GmSEXI4TAp https://t.co/FDeUZ8XBhy",
      "likes": 0,
      "reposts": 0,
      "replies": 0,
      "time": "Fri Mar 13 22:19:03 +0000 2026",
      "link": "https://x.com/CAStolzenbach/status/2032582235006570510",
      "tag": "67"
    },
    {
      "id": "2032582215188578557",
      "user": "promoimperdivel",
      "text": "PACO RABANNE BLACK XS DO CLT\n\n\ud83e\udd29 Paris Elysees Tradicional Perfume Black Shark Paris Elysses Edt 100ml\n\n\ud83d\ude35 De: 117\n\ud83e\udd11 Por: R$ 67\n\n\ud83d\uded2 Compre aqui: https://t.co/wKGZORsTUa\n\nloja oficial paris elysees https://t.co/1qSFuw9cDk",
      "likes": 0,
      "reposts": 0,
      "replies": 0,
      "time": "Fri Mar 13 22:18:58 +0000 2026",
      "link": "https://x.com/promoimperdivel/status/2032582215188578557",
      "tag": "67"
    },
    {
      "id": "2032582205080482302",
      "user": "Palosolo67azul",
      "text": "@TheChipi Ese til\u00edn es masoquista le est\u00e1n dando en el suelo y a\u00fan pide que lo rematen.",
      "likes": 0,
      "reposts": 0,
      "replies": 0,
      "time": "Fri Mar 13 22:18:55 +0000 2026",
      "link": "https://x.com/Palosolo67azul/status/2032582205080482302",
      "tag": "$67"
    },
    {
      "id": "2032582179306500309",
      "user": "MarkBuck753136",
      "text": "@MbarkCherguia inverted 67",
      "likes": 0,
      "reposts": 0,
      "replies": 0,
      "time": "Fri Mar 13 22:18:49 +0000 2026",
      "link": "https://x.com/MarkBuck753136/status/2032582179306500309",
      "tag": "67"
    },
    {
      "id": "2032582173471936845",
      "user": "steinguide",
      "text": "A teaser from my coming short book on future telecoms: \"Latency below 10^\u221267 s and potential bandwidth above 10^75 Hz are why direct facelock COI systems belong to a different class of communication altogether.\"",
      "likes": 0,
      "reposts": 0,
      "replies": 0,
      "time": "Fri Mar 13 22:18:48 +0000 2026",
      "link": "https://x.com/steinguide/status/2032582173471936845",
      "tag": "67"
    },
    {
      "id": "2032582133810602456",
      "user": "hacomarps",
      "text": "Que co\u00f1o es lo de six Seven?",
      "likes": 0,
      "reposts": 0,
      "replies": 0,
      "time": "Fri Mar 13 22:18:38 +0000 2026",
      "link": "https://x.com/hacomarps/status/2032582133810602456",
      "tag": "Six Seven"
    },
    {
      "id": "2032582119239856596",
      "user": "Qurnia87",
      "text": "@ShopeeID Fitur favoritku di realme 16 5G adalah kamera 200MP Portrait yang menghasilkan foto super detail dan tajam. Cocok untuk foto produk, bikin konten, dan mengabadikan momen Ramadan dan Lebaran. Performa cepat &amp; baterai besar bikin nyaman dipakai seharian\n#realme16Serie",
      "likes": 0,
      "reposts": 0,
      "replies": 0,
      "time": "Fri Mar 13 22:18:35 +0000 2026",
      "link": "https://x.com/Qurnia87/status/2032582119239856596",
      "tag": "67"
    },
    {
      "id": "2032582043251638617",
      "user": "starrrgazed",
      "text": "if i made a new account how many people would actually follow it",
      "likes": 0,
      "reposts": 0,
      "replies": 0,
      "time": "Fri Mar 13 22:18:17 +0000 2026",
      "link": "https://x.com/starrrgazed/status/2032582043251638617",
      "tag": "$67"
    },
    {
      "id": "2032582030194511938",
      "user": "Leyla5xxe",
      "text": "@FanMaga12551 67",
      "likes": 1,
      "reposts": 0,
      "replies": 0,
      "time": "Fri Mar 13 22:18:14 +0000 2026",
      "link": "https://x.com/Leyla5xxe/status/2032582030194511938",
      "tag": "67"
    },
    {
      "id": "2032582024129605918",
      "user": "PromoTrem",
      "text": "Perfume Paris Elysees Black Shark 100ml Masculino\n\n\ud83d\udd25 De R$67 por R$49 (at\u00e9 3x de R$22,33)\n\n\ud83d\uded2 https://t.co/xhWlxxHcuk\n\n\ud83d\udcf2 Link do grupo de ofertas: https://t.co/mQzHEVwjI5 Rayhaan Nocturno EDP 100ml\n\n\ud83d\udd25 De R$489 por R$290\n\n\ud83d\uded2 https://t.co/fApmthVDi1\n\n\ud83d\udcf2 Link do grupo de ofertas:",
      "likes": 0,
      "reposts": 0,
      "replies": 0,
      "time": "Fri Mar 13 22:18:12 +0000 2026",
      "link": "https://x.com/PromoTrem/status/2032582024129605918",
      "tag": "67"
    },
    {
      "id": "2032581982509514995",
      "user": "kittenfacerb",
      "text": "@CrimsonHaze2 people ALWAYS talk about seven but everyone forgets about her twin sister six wtf is wrong with this fandom",
      "likes": 2,
      "reposts": 0,
      "replies": 0,
      "time": "Fri Mar 13 22:18:02 +0000 2026",
      "link": "https://x.com/kittenfacerb/status/2032581982509514995",
      "tag": "Six Seven"
    },
    {
      "id": "2032581976612380984",
      "user": "zencar941",
      "text": "Day 67 shilling $peezy till we get to $20M \n\n@peezyethereum 0x698b1d54e936b9f772b8f58447194bbc82ec1933 https://t.co/7REPcs58Au",
      "likes": 0,
      "reposts": 0,
      "replies": 0,
      "time": "Fri Mar 13 22:18:01 +0000 2026",
      "link": "https://x.com/zencar941/status/2032581976612380984",
      "tag": "67"
    },
    {
      "id": "2032581956899094950",
      "user": "slugalung",
      "text": "YESSSS GIVE US 67 POPPY PLAYTIME GAMESSSS",
      "likes": 0,
      "reposts": 0,
      "replies": 0,
      "time": "Fri Mar 13 22:17:56 +0000 2026",
      "link": "https://x.com/slugalung/status/2032581956899094950",
      "tag": "67"
    },
    {
      "id": "2032581891111686161",
      "user": "nanafrania",
      "text": "@vamzzan 67",
      "likes": 0,
      "reposts": 0,
      "replies": 0,
      "time": "Fri Mar 13 22:17:41 +0000 2026",
      "link": "https://x.com/nanafrania/status/2032581891111686161",
      "tag": "67"
    },
    {
      "id": "2032581862728573435",
      "user": "AnaMariasizxs",
      "text": "@sanchezcastejon Que guerra hijo de puta si tu le has dado dinero a Hamas y a los Castros que llevan 67 a\u00f1os masacrando a Cuba , si tu te beneficiaste del Narco Terrorista Dictador Maduro! De que cojones de paz tu hablas si tu solo apoyas dictadores y terroristas",
      "likes": 0,
      "reposts": 0,
      "replies": 0,
      "time": "Fri Mar 13 22:17:34 +0000 2026",
      "link": "https://x.com/AnaMariasizxs/status/2032581862728573435",
      "tag": "67"
    },
    {
      "id": "2032581861151510957",
      "user": "IsHePlayingTN",
      "text": "\ud83d\udea8 Jeremy Sochan (Knicks) is OUT (32nd game missed this season)\n\n\ud83c\udfc0 Jeremy Sochan This Season (37 Games)\n11.0 MPG | 3.3 PPG | 2.3 RPG | 0.9 APG | 3.0 FGA\n\n\ud83d\udcca Team Impact:\nRecord: 6-3 (67%) \u2192 35-21 (63%) (-4%)\nORtg: 115.0 \u2192 118.6 (+3.6)\nDRtg: 105.3 \u2192 112.8 (+7.5)\nNRtg: +9.7 \u2192 https:/",
      "likes": 0,
      "reposts": 0,
      "replies": 0,
      "time": "Fri Mar 13 22:17:33 +0000 2026",
      "link": "https://x.com/IsHePlayingTN/status/2032581861151510957",
      "tag": "67"
    },
    {
      "id": "2032581756952429034",
      "user": "Xboxplayer13",
      "text": "@paularambles hehe six seven",
      "likes": 0,
      "reposts": 0,
      "replies": 0,
      "time": "Fri Mar 13 22:17:09 +0000 2026",
      "link": "https://x.com/Xboxplayer13/status/2032581756952429034",
      "tag": "Six Seven"
    },
    {
      "id": "2032581739961282967",
      "user": "DPlag023",
      "text": "Recuerden que el gobierno catrista tiene 67 a\u00f1os... literalmente morir\u00e1 por el meme m\u00e1s pelotudo six seven",
      "likes": 0,
      "reposts": 0,
      "replies": 0,
      "time": "Fri Mar 13 22:17:05 +0000 2026",
      "link": "https://x.com/DPlag023/status/2032581739961282967",
      "tag": "Six Seven"
    },
    {
      "id": "2032581497614377455",
      "user": "chruixx",
      "text": "six seven",
      "likes": 0,
      "reposts": 0,
      "replies": 0,
      "time": "Fri Mar 13 22:16:07 +0000 2026",
      "link": "https://x.com/chruixx/status/2032581497614377455",
      "tag": "Six Seven"
    },
    {
      "id": "2032581224779157681",
      "user": "jkkcocaina",
      "text": "Six seven",
      "likes": 0,
      "reposts": 0,
      "replies": 0,
      "time": "Fri Mar 13 22:15:02 +0000 2026",
      "link": "https://x.com/jkkcocaina/status/2032581224779157681",
      "tag": "Six Seven"
    },
    {
      "id": "2032580662528544982",
      "user": "imaistrying",
      "text": "i thought this was a six seven joke wtf.",
      "likes": 0,
      "reposts": 0,
      "replies": 0,
      "time": "Fri Mar 13 22:12:48 +0000 2026",
      "link": "https://x.com/imaistrying/status/2032580662528544982",
      "tag": "Six Seven"
    },
    {
      "id": "2032580243651961080",
      "user": "NMLobo4Ever",
      "text": "@LouisLobo496622 I understand what you're saying but they're going to need his length against the Aztecs badly. We just go Seven in the rotation as it is. I have been wanting to see him out of the starting lineup for six weeks but they do need him off the bench. He looked a lot b",
      "likes": 0,
      "reposts": 0,
      "replies": 0,
      "time": "Fri Mar 13 22:11:08 +0000 2026",
      "link": "https://x.com/NMLobo4Ever/status/2032580243651961080",
      "tag": "Six Seven"
    },
    {
      "id": "2032580106053431385",
      "user": "ch4ngerry",
      "text": "@ansx1d SIX SEVEN https://t.co/S3tQsW64dC",
      "likes": 0,
      "reposts": 0,
      "replies": 0,
      "time": "Fri Mar 13 22:10:35 +0000 2026",
      "link": "https://x.com/ch4ngerry/status/2032580106053431385",
      "tag": "Six Seven"
    },
    {
      "id": "2032579859197682043",
      "user": "unprogramming",
      "text": "German Chancellor Merz: Six out of seven G7 countries were clearly of the opinion that sanctions against Russia should not be lifted. We were somewhat surprised to hear this morning that the American government had decided differently. That is definitely not our view. We believ\u2026",
      "likes": 0,
      "reposts": 0,
      "replies": 0,
      "time": "Fri Mar 13 22:09:36 +0000 2026",
      "link": "https://x.com/unprogramming/status/2032579859197682043",
      "tag": "Six Seven"
    },
    {
      "id": "2032579758890922136",
      "user": "mysteriousbiu",
      "text": "@doyoungcareca @strwbrryzz_ \ud83d\ude4f\ud83d\ude4f\ud83d\ude4f\ud83d\ude4f\n\nENHYPEN IS SEVEN. NO SIX. #BELIFTLABTREATENHYPENBETTER #ENHYPEN_IS_7 \n#sevEN_ALWAYSENHYPEN \n#OT7_FOREVER \n#enhypen7forever \n#HEESEUNG_IS_ENHYPEN",
      "likes": 1,
      "reposts": 1,
      "replies": 0,
      "time": "Fri Mar 13 22:09:12 +0000 2026",
      "link": "https://x.com/mysteriousbiu/status/2032579758890922136",
      "tag": "Six Seven"
    },
    {
      "id": "2032579558382383307",
      "user": "Brainmetry",
      "text": "@pbeisel I believe the original idea, which I want to believe is still true, is to simulate any companies that their output/production is digital or software.  Six out of the seven companies in Mag 7 are.  This means anyone can potentially start a multibillion-dollar corporation.",
      "likes": 0,
      "reposts": 0,
      "replies": 0,
      "time": "Fri Mar 13 22:08:24 +0000 2026",
      "link": "https://x.com/Brainmetry/status/2032579558382383307",
      "tag": "Six Seven"
    },
    {
      "id": "2032579453524558222",
      "user": "femboyofthey3ar",
      "text": "@kittnpw what r u like six seven or maybe john pork, maybe tung tung tung tung tung kill me bruh pls help tung tung tung",
      "likes": 0,
      "reposts": 0,
      "replies": 0,
      "time": "Fri Mar 13 22:07:59 +0000 2026",
      "link": "https://x.com/femboyofthey3ar/status/2032579453524558222",
      "tag": "Six Seven"
    },
    {
      "id": "2032579162989359306",
      "user": "mysteriousbiu",
      "text": "@smoothpjs @YunieMeows ENHYPEN IS SEVEN. NO SIX. #BELIFTLABTREATENHYPENBETTER #ENHYPEN_IS_7 \n#sevEN_ALWAYSENHYPEN \n#OT7_FOREVER \n#enhypen7forever \n#HEESEUNG_IS_ENHYPEN",
      "likes": 0,
      "reposts": 0,
      "replies": 0,
      "time": "Fri Mar 13 22:06:50 +0000 2026",
      "link": "https://x.com/mysteriousbiu/status/2032579162989359306",
      "tag": "Six Seven"
    },
    {
      "id": "2032579121042305333",
      "user": "moonstrvcken",
      "text": "support all member specially six in melbourne and drop ht for one more. ENHYPEN IS SEVEN, no matter what. if you won\u2019t, don\u2019t be annoying then make people want to give up.",
      "likes": 0,
      "reposts": 0,
      "replies": 1,
      "time": "Fri Mar 13 22:06:40 +0000 2026",
      "link": "https://x.com/moonstrvcken/status/2032579121042305333",
      "tag": "Six Seven"
    },
    {
      "id": "2032504278422868292",
      "user": "wjponchain",
      "text": "I genuinely believe people will be shocked where 67 is heading in season 2.\n\nSeason 1: Power of The Youth.\nSeason 2: Giving Power To The Youth.\n\n#67to67billion https://t.co/bLU5qrULdK",
      "likes": 52,
      "reposts": 16,
      "replies": 19,
      "time": "Fri Mar 13 17:09:16 +0000 2026",
      "link": "https://x.com/wjponchain/status/2032504278422868292",
      "tag": "67to67billion"
    },
    {
      "id": "2032480114068328923",
      "user": "HarrodFrances",
      "text": "@CryptoCurb #67to67billion https://t.co/kgytJv34Ka",
      "likes": 1,
      "reposts": 0,
      "replies": 0,
      "time": "Fri Mar 13 15:33:15 +0000 2026",
      "link": "https://x.com/HarrodFrances/status/2032480114068328923",
      "tag": "67to67billion"
    }
  ],
  "x_popular": [
    {
      "text": "0.5 $SOL Giveaway ( $67 ) \n\n\u2022 Follow @octovpnsolana with \ud83d\udd14\n\u2022 Drop your $SOL wallet\n\u2022 Retweet &amp; Like \n\n120 mins watch \u23f0",
      "user": "doji",
      "handle": "dojixsol",
      "time": "2026-01-05T16:04:52+00:00",
      "link": "https://x.com/dojixsol/status/2008208082917278101",
      "tweet_url": "https://x.com/dojixsol/status/2008208082917278101",
      "likes": 287,
      "reposts": 235,
      "replies": 305
    },
    {
      "text": "All time high in 2025\n\nBitcoin: $126,210\nEthereum: $4,946\nSolana: $294\n\nToday\u2019s price\n\nBitcoin: $67,000\nEthereum: $2,000\nSolana: $84\n\nWhat\u2019s the lesson here?",
      "user": "Uzi",
      "handle": "UziCryptoo",
      "time": "2026-03-07T19:17:47+00:00",
      "link": "https://x.com/UziCryptoo/status/2030362292811129021",
      "tweet_url": "https://x.com/UziCryptoo/status/2030362292811129021",
      "likes": 543,
      "reposts": 23,
      "replies": 207
    },
    {
      "text": "The Official 67 Coin ($67) is now verified on Moonshot. https://t.co/dhpDRxAUoq",
      "user": "Moonshot",
      "handle": "moonshot",
      "time": "2025-11-19T02:32:44+00:00",
      "link": "https://x.com/moonshot/status/1990971475751285126",
      "tweet_url": "https://x.com/moonshot/status/1990971475751285126",
      "likes": 415,
      "reposts": 78,
      "replies": 140
    },
    {
      "text": "Solana Memecoins with Highest Growth in the Last 7 Days \ud83c\udf1f \n\n\ud83d\udd38RALPH | $RALPH\n\ud83d\udd38SOLTOMATO | $SOLTOMATO\n\ud83d\udd38Groyper| @GroyperSol\n\ud83d\udd3867 | #67coin\n\ud83d\udd38HEGE | @HegeCoin\n\ud83d\udd38retire | @thelastplaysol\n\ud83d\udd38LOOK | @lookdotfun\n\ud83d\udd38ANONCOIN | @anoncoinit\n\ud83d\udd38MIM  | @mimcoinbtc\n\ud83d\udd38Clash | @GeorgePlayClash https://t.",
      "user": "Solana Daily",
      "handle": "solana_daily",
      "time": "2026-01-16T11:03:57+00:00",
      "link": "https://x.com/solana_daily/status/2012118622702125490",
      "tweet_url": "https://x.com/solana_daily/status/2012118622702125490",
      "likes": 244,
      "reposts": 162,
      "replies": 169
    },
    {
      "text": "52 days ago this wallet bought $430 67Coin and now $134,000 in profit which sold $62,200 so far. https://t.co/a3lo66LC0t",
      "user": "Kakashi",
      "handle": "kkashi_yt",
      "time": "2025-09-08T08:27:24+00:00",
      "link": "https://x.com/kkashi_yt/status/1964968803814776914",
      "tweet_url": "https://x.com/kkashi_yt/status/1964968803814776914",
      "likes": 431,
      "reposts": 13,
      "replies": 41
    },
    {
      "text": "Been in $67 since 41.5k MC \nFeels good \ud83d\ude42\u200d\u2194\ufe0f #67 https://t.co/EtjjlNRaa3",
      "user": "solina",
      "handle": "sol_inaa",
      "time": "2025-09-09T19:24:52+00:00",
      "link": "https://x.com/sol_inaa/status/1965496646651007347",
      "tweet_url": "https://x.com/sol_inaa/status/1965496646651007347",
      "likes": 350,
      "reposts": 8,
      "replies": 40
    },
    {
      "text": "67 is still the biggest fumble of the trenches and it\u2019s not even close\n\nif you would\u2019ve let those TikTok cabal kids that push larp elon and trump coins every week run 67 instead, they would have sent it to a billion\n\nwhat would the trenches look like today with a 10 fig 67 coin?",
      "user": "Jack Duval\ud83c\udf0a",
      "handle": "jackduval",
      "time": "2026-02-18T04:12:35+00:00",
      "link": "https://x.com/jackduval/status/2023973895829848278",
      "tweet_url": "https://x.com/jackduval/status/2023973895829848278",
      "likes": 289,
      "reposts": 7,
      "replies": 84
    },
    {
      "text": "The Official 67 Coin\n\n7.2M -&gt; 42.2M and counting \n\nthis is the ultimate generational wealth play. you aren\u2019t late until it\u2019s at six seven billion \ud83d\udc8e https://t.co/NOlzvppZsk",
      "user": "100x",
      "handle": "100xgemfinder",
      "time": "2025-11-18T23:00:01+00:00",
      "link": "https://x.com/100xgemfinder/status/1990917941412479428",
      "tweet_url": "https://x.com/100xgemfinder/status/1990917941412479428",
      "likes": 135,
      "reposts": 24,
      "replies": 32
    },
    {
      "text": "Think something absolutely crazy will happen as we saw it on #67coin as well.\n\n$FKH is going nuts on PumpFun.\n\nBacked by the Flying Ketamine Horse creator which is also receiving the fees finally.\n\nEs4f2qodnhBAkPgDNp8F7emQLhZKe5fEiSghNXSDpump https://t.co/A6ibDvrQ8p",
      "user": "mrpatrickschmitt",
      "handle": "mr_pschmitt",
      "time": "2026-01-08T04:46:10+00:00",
      "link": "https://x.com/mr_pschmitt/status/2009124446829719564",
      "tweet_url": "https://x.com/mr_pschmitt/status/2009124446829719564",
      "likes": 105,
      "reposts": 27,
      "replies": 28
    },
    {
      "text": "Had to get off early yesterday, but made a calm 67 solanas\n\nToday we continue the grind\n\nLive trading here:\n\nhttps://t.co/UO4GG7v8Gs https://t.co/vlnppAhp34",
      "user": "decu",
      "handle": "notdecu",
      "time": "2026-03-05T15:34:42+00:00",
      "link": "https://x.com/notdecu/status/2029581375683154391",
      "tweet_url": "https://x.com/notdecu/status/2029581375683154391",
      "likes": 132,
      "reposts": 11,
      "replies": 38
    },
    {
      "text": "Two numbers to unite the world. 67 billion human beings.\n\n@duolingo \n\n#67to67billion https://t.co/NxWQIuCAZG",
      "user": "The Official 67 Coin",
      "handle": "67coinX",
      "time": "2026-03-07T16:18:50+00:00",
      "link": "https://x.com/67coinX/status/2030317259894218981",
      "tweet_url": "https://x.com/67coinX/status/2030317259894218981",
      "likes": 79,
      "reposts": 18,
      "replies": 24
    },
    {
      "text": "$67 - $22.12M MCap\n\nCA: 9AvytnUKsLxPxFHFqS6VLxaxt5p6BhYNr53SD2Chpump\n\nIt went viral from a clip of a kid excitedly repeating \u2018six seven\u2019 while reading the Bible at church. The clip was later reshared by JD Vance in a widely circulated post.\n\nIt's pumping so strong\n\n#DYOR https://",
      "user": "Solana Daily",
      "handle": "solana_daily",
      "time": "2025-12-10T11:19:52+00:00",
      "link": "https://x.com/solana_daily/status/1998714277553971617",
      "tweet_url": "https://x.com/solana_daily/status/1998714277553971617",
      "likes": 82,
      "reposts": 8,
      "replies": 11
    },
    {
      "text": "Pump and 67 on the streets. \n\n\ud83e\udef4\n    \ud83e\udef4\n\n#67to67Billion https://t.co/6NaCHHJZkJ",
      "user": "The Official 67 Coin",
      "handle": "67coinX",
      "time": "2026-02-26T18:16:22+00:00",
      "link": "https://x.com/67coinX/status/2027085345792377118",
      "tweet_url": "https://x.com/67coinX/status/2027085345792377118",
      "likes": 58,
      "reposts": 17,
      "replies": 24
    },
    {
      "text": "45M was the warm up.\nEarly. Season 2 loading...\n\ud83e\udef4\n    \ud83e\udef4\n\n#67to67Billion",
      "user": "The Official 67 Coin",
      "handle": "67coinX",
      "time": "2026-03-04T16:51:43+00:00",
      "link": "https://x.com/67coinX/status/2029238368824115654",
      "tweet_url": "https://x.com/67coinX/status/2029238368824115654",
      "likes": 53,
      "reposts": 18,
      "replies": 17
    },
    {
      "text": "Austrians definitely know how to 67.\n\nThe biggest meme mindshare in human history. Period.\n\n#67to67billion https://t.co/qUYodxsv8w",
      "user": "The Official 67 Coin",
      "handle": "67coinX",
      "time": "2026-03-04T14:46:46+00:00",
      "link": "https://x.com/67coinX/status/2029206927318614276",
      "tweet_url": "https://x.com/67coinX/status/2029206927318614276",
      "likes": 55,
      "reposts": 17,
      "replies": 15
    },
    {
      "text": "More submissions coming in for the 67 community Discord's sticker contest.\n\n1,500 members strong.\n\nRetail onboarding in real time.\n\nJoin at https://t.co/lJsmo7Ag4I\n\n#67to67billion https://t.co/vyASuB5eqT",
      "user": "The Official 67 Coin",
      "handle": "67coinX",
      "time": "2026-02-20T18:21:26+00:00",
      "link": "https://x.com/67coinX/status/2024912293541155314",
      "tweet_url": "https://x.com/67coinX/status/2024912293541155314",
      "likes": 44,
      "reposts": 11,
      "replies": 19
    },
    {
      "text": "$67\n\nsix-seven is going to $67M (and then higher)\n\n#67to67Billion https://t.co/4pmWys6yuw",
      "user": "curb.sol",
      "handle": "CryptoCurb",
      "time": "2026-01-15T20:50:50+00:00",
      "link": "https://x.com/CryptoCurb/status/2011903928791896317",
      "tweet_url": "https://x.com/CryptoCurb/status/2011903928791896317",
      "likes": 49,
      "reposts": 8,
      "replies": 22
    },
    {
      "text": "Still holding my $Youngho and maybe it might take weeks as #67coin and $Whitewhale did to take of.\n\nDoubt it will die since the trend on tiktok is growing.\n\nMoon or dust.\n\nBmsRvPgXrgXXEn67RBBoAu3NCjDFE72Zb1nkMf7kpump",
      "user": "mrpatrickschmitt",
      "handle": "mr_pschmitt",
      "time": "2026-02-01T04:37:12+00:00",
      "link": "https://x.com/mr_pschmitt/status/2017819497134985518",
      "tweet_url": "https://x.com/mr_pschmitt/status/2017819497134985518",
      "likes": 33,
      "reposts": 12,
      "replies": 7
    },
    {
      "text": "Thanks for this candle, CZ.\n\n#67coin is not just a 2025 trending, you mean right? https://t.co/A9fK1HoOw1",
      "user": "\ud83d\udd75\ufe0fGEM DETECTER\ud83d\udd75\ufe0f",
      "handle": "gem_detecter",
      "time": "2026-01-15T16:50:56+00:00",
      "link": "https://x.com/gem_detecter/status/2011843554294059466",
      "tweet_url": "https://x.com/gem_detecter/status/2011843554294059466",
      "likes": 43,
      "reposts": 6,
      "replies": 39
    },
    {
      "text": "Gm 67whale CT \n\n#67Whale : $9.6 k MC and #67coin : $30 m MC\n\nWhen the CTO movement will start on 67Whale nothing should stop us.\n\nThe best projects come from CTOs\n\nCA :\n\n2TSC2PaXZDCkrBoxcNBiQyWh61dC9bRGqL8nKwfbpump\n\nBe ready to invade the internet 67 Whale Supporter. https://t.co",
      "user": "CyrDoge",
      "handle": "cyrdoge",
      "time": "2026-01-15T08:51:03+00:00",
      "link": "https://x.com/cyrdoge/status/2011722788755652728",
      "tweet_url": "https://x.com/cyrdoge/status/2011722788755652728",
      "likes": 24,
      "reposts": 15,
      "replies": 9
    }
  ],
  "x_notifications": [
    {
      "id": "3726086017629471842",
      "text": "It's over. It's code in your heart, in your soul. You will never be the same after 67.\n\n#67mindvirus",
      "user": "",
      "handle": "",
      "link": "",
      "time": "2026-03-04T01:04:23.172Z",
      "likes": 0,
      "reposts": 0,
      "replies": 0
    },
    {
      "id": "4965481619453659487",
      "text": "When 67 on Chinese",
      "user": "",
      "handle": "",
      "link": "",
      "time": "2026-03-03T22:34:10.334Z",
      "likes": 0,
      "reposts": 0,
      "replies": 0
    },
    {
      "id": "4780387493253780684",
      "text": "Already in. Already up.\n\n6 \n7",
      "user": "",
      "handle": "",
      "link": "",
      "time": "2026-03-03T13:07:35.980Z",
      "likes": 0,
      "reposts": 0,
      "replies": 0
    },
    {
      "id": "6065174400989761352",
      "text": "Join us kingstaccz",
      "user": "",
      "handle": "",
      "link": "",
      "time": "2026-03-02T21:59:37.490Z",
      "likes": 0,
      "reposts": 0,
      "replies": 0
    },
    {
      "id": "909205826982791646",
      "text": "Pause on 67",
      "user": "",
      "handle": "",
      "link": "",
      "time": "2026-03-02T16:34:52.109Z",
      "likes": 0,
      "reposts": 0,
      "replies": 0
    },
    {
      "id": "3405922706086456742",
      "text": "Coded",
      "user": "",
      "handle": "",
      "link": "",
      "time": "2026-03-02T16:19:39.366Z",
      "likes": 0,
      "reposts": 0,
      "replies": 0
    },
    {
      "id": "498342045763499120",
      "text": "More 67",
      "user": "",
      "handle": "",
      "link": "",
      "time": "2026-03-02T14:07:38.192Z",
      "likes": 0,
      "reposts": 0,
      "replies": 0
    }
  ],
  "x_best_48h": [
    {
      "text": "These pump fun coins are gaining traction! \n\n$BigTrout +120%\n$67 +67%\n$DOLAN +89%\n\nWhich one you holding?",
      "handle": "67coinX",
      "user": "The Official 67 Coin",
      "time": "2026-02-07T00:00:00Z",
      "link": "https://x.com/67coinX",
      "likes": 291,
      "reposts": 0,
      "replies": 0
    },
    {
      "text": "German influencers with millions on TikTok and other socials are starting to talk about $67",
      "handle": "67coinX",
      "user": "The Official 67 Coin",
      "time": "2026-02-07T00:00:00Z",
      "link": "https://x.com/67coinX",
      "likes": 57,
      "reposts": 0,
      "replies": 0
    }
  ],
  "_snapshot_7d": {
    "twitter_followers": 1670,
    "x_community_members": 9919,
    "total_views_recent": 30682,
    "total_likes_recent": 886,
    "engagement_rate": 4.862,
    "timestamp": 1772846314.1583,
    "date": "2026-03-07"
  },
  "x_news_updated": "2026-03-07T02:45:14.859344+00:00",
  "x_latest_updated": "2026-03-13T22:20:13.776254+00:00",
  "x_popular_updated": "2026-03-11T00:35:19.302218+00:00"
}